[{"code":"ff_CM","name":"Fulah (Cameroon)"},{"code":"ff_GN","name":"Fulah (Guinea)"},{"code":"ff_MR","name":"Fulah (Mauritania)"},{"code":"ff_SN","name":"Fulah (Senegal)"},{"code":"tl_PH","name":"Tagalog (Philippines)"},{"code":"az_AZ","name":"\u10d0\u10d6\u10d4\u10e0\u10d1\u10d0\u10d8\u10ef\u10d0\u10dc\u10e3\u10da\u10d8 (\u10d0\u10d6\u10d4\u10e0\u10d1\u10d0\u10d8\u10ef\u10d0\u10dc\u10d8)"},{"code":"ak_GH","name":"\u10d0\u10d9\u10d0\u10dc\u10d8 (\u10d2\u10d0\u10dc\u10d0)"},{"code":"sq_AL","name":"\u10d0\u10da\u10d1\u10d0\u10dc\u10e3\u10e0\u10d8 (\u10d0\u10da\u10d1\u10d0\u10dc\u10d4\u10d7\u10d8)"},{"code":"sq_XK","name":"\u10d0\u10da\u10d1\u10d0\u10dc\u10e3\u10e0\u10d8 (\u10d9\u10dd\u10e1\u10dd\u10d5\u10dd)"},{"code":"sq_MK","name":"\u10d0\u10da\u10d1\u10d0\u10dc\u10e3\u10e0\u10d8 (\u10db\u10d0\u10d9\u10d4\u10d3\u10dd\u10dc\u10d8\u10d0)"},{"code":"am_ET","name":"\u10d0\u10db\u10f0\u10d0\u10e0\u10e3\u10da\u10d8 (\u10d4\u10d7\u10d8\u10dd\u10de\u10d8\u10d0)"},{"code":"ar_DZ","name":"\u10d0\u10e0\u10d0\u10d1\u10e3\u10da\u10d8 (\u10d0\u10da\u10df\u10d8\u10e0\u10d8)"},{"code":"ar_AE","name":"\u10d0\u10e0\u10d0\u10d1\u10e3\u10da\u10d8 (\u10d0\u10e0\u10d0\u10d1\u10d7\u10d0 \u10d2\u10d0\u10d4\u10e0\u10d7\u10d8\u10d0\u10dc\u10d4\u10d1\u10e3\u10da\u10d8 \u10e1\u10d0\u10d0\u10db\u10d8\u10e0\u10dd\u10d4\u10d1\u10d8)"},{"code":"ar_BH","name":"\u10d0\u10e0\u10d0\u10d1\u10e3\u10da\u10d8 (\u10d1\u10d0\u10f0\u10e0\u10d4\u10d8\u10dc\u10d8)"},{"code":"ar_EH","name":"\u10d0\u10e0\u10d0\u10d1\u10e3\u10da\u10d8 (\u10d3\u10d0\u10e1\u10d0\u10d5\u10da\u10d4\u10d7\u10d8 \u10e1\u10d0\u10f0\u10d0\u10e0\u10d0)"},{"code":"ar_EG","name":"\u10d0\u10e0\u10d0\u10d1\u10e3\u10da\u10d8 (\u10d4\u10d2\u10d5\u10d8\u10de\u10e2\u10d4)"},{"code":"ar_IQ","name":"\u10d0\u10e0\u10d0\u10d1\u10e3\u10da\u10d8 (\u10d4\u10e0\u10d0\u10e7\u10d8)"},{"code":"ar_ER","name":"\u10d0\u10e0\u10d0\u10d1\u10e3\u10da\u10d8 (\u10d4\u10e0\u10d8\u10e2\u10e0\u10d4\u10d0)"},{"code":"ar_YE","name":"\u10d0\u10e0\u10d0\u10d1\u10e3\u10da\u10d8 (\u10d8\u10d4\u10db\u10d4\u10dc\u10d8)"},{"code":"ar_JO","name":"\u10d0\u10e0\u10d0\u10d1\u10e3\u10da\u10d8 (\u10d8\u10dd\u10e0\u10d3\u10d0\u10dc\u10d8\u10d0)"},{"code":"ar_IL","name":"\u10d0\u10e0\u10d0\u10d1\u10e3\u10da\u10d8 (\u10d8\u10e1\u10e0\u10d0\u10d4\u10da\u10d8)"},{"code":"ar_QA","name":"\u10d0\u10e0\u10d0\u10d1\u10e3\u10da\u10d8 (\u10d9\u10d0\u10e2\u10d0\u10e0\u10d8)"},{"code":"ar_KM","name":"\u10d0\u10e0\u10d0\u10d1\u10e3\u10da\u10d8 (\u10d9\u10dd\u10db\u10dd\u10e0\u10d8\u10e1 \u10d9\u10e3\u10dc\u10eb\u10e3\u10da\u10d4\u10d1\u10d8)"},{"code":"ar_LB","name":"\u10d0\u10e0\u10d0\u10d1\u10e3\u10da\u10d8 (\u10da\u10d8\u10d1\u10d0\u10dc\u10d8)"},{"code":"ar_LY","name":"\u10d0\u10e0\u10d0\u10d1\u10e3\u10da\u10d8 (\u10da\u10d8\u10d1\u10d8\u10d0)"},{"code":"ar_MR","name":"\u10d0\u10e0\u10d0\u10d1\u10e3\u10da\u10d8 (\u10db\u10d0\u10d5\u10e0\u10d8\u10e2\u10d0\u10dc\u10d8\u10d0)"},{"code":"ar_MA","name":"\u10d0\u10e0\u10d0\u10d1\u10e3\u10da\u10d8 (\u10db\u10d0\u10e0\u10dd\u10d9\u10dd)"},{"code":"ar_OM","name":"\u10d0\u10e0\u10d0\u10d1\u10e3\u10da\u10d8 (\u10dd\u10db\u10d0\u10dc\u10d8)"},{"code":"ar_PS","name":"\u10d0\u10e0\u10d0\u10d1\u10e3\u10da\u10d8 (\u10de\u10d0\u10da\u10d4\u10e1\u10e2\u10d8\u10dc\u10d8\u10e1 \u10e2\u10d4\u10e0\u10d8\u10e2\u10dd\u10e0\u10d8\u10d4\u10d1\u10d8)"},{"code":"ar_SS","name":"\u10d0\u10e0\u10d0\u10d1\u10e3\u10da\u10d8 (\u10e1\u10d0\u10db\u10ee\u10e0\u10d4\u10d7\u10d8 \u10e1\u10e3\u10d3\u10d0\u10dc\u10d8)"},{"code":"ar_SA","name":"\u10d0\u10e0\u10d0\u10d1\u10e3\u10da\u10d8 (\u10e1\u10d0\u10e3\u10d3\u10d8\u10e1 \u10d0\u10e0\u10d0\u10d1\u10d4\u10d7\u10d8)"},{"code":"ar_SY","name":"\u10d0\u10e0\u10d0\u10d1\u10e3\u10da\u10d8 (\u10e1\u10d8\u10e0\u10d8\u10d0)"},{"code":"ar_SO","name":"\u10d0\u10e0\u10d0\u10d1\u10e3\u10da\u10d8 (\u10e1\u10dd\u10db\u10d0\u10da\u10d8)"},{"code":"ar_SD","name":"\u10d0\u10e0\u10d0\u10d1\u10e3\u10da\u10d8 (\u10e1\u10e3\u10d3\u10d0\u10dc\u10d8)"},{"code":"ar_TN","name":"\u10d0\u10e0\u10d0\u10d1\u10e3\u10da\u10d8 (\u10e2\u10e3\u10dc\u10d8\u10e1\u10d8)"},{"code":"ar_KW","name":"\u10d0\u10e0\u10d0\u10d1\u10e3\u10da\u10d8 (\u10e5\u10e3\u10d5\u10d4\u10d8\u10d7\u10d8)"},{"code":"ar_TD","name":"\u10d0\u10e0\u10d0\u10d1\u10e3\u10da\u10d8 (\u10e9\u10d0\u10d3\u10d8)"},{"code":"ar_DJ","name":"\u10d0\u10e0\u10d0\u10d1\u10e3\u10da\u10d8 (\u10ef\u10d8\u10d1\u10e3\u10e2\u10d8)"},{"code":"as_IN","name":"\u10d0\u10e1\u10d0\u10db\u10e3\u10e0\u10d8 (\u10d8\u10dc\u10d3\u10dd\u10d4\u10d7\u10d8)"},{"code":"af_NA","name":"\u10d0\u10e4\u10e0\u10d8\u10d9\u10d0\u10d0\u10dc\u10e1\u10d8 (\u10dc\u10d0\u10db\u10d8\u10d1\u10d8\u10d0)"},{"code":"af_ZA","name":"\u10d0\u10e4\u10e0\u10d8\u10d9\u10d0\u10d0\u10dc\u10e1\u10d8 (\u10e1\u10d0\u10db\u10ee\u10e0\u10d4\u10d7 \u10d0\u10e4\u10e0\u10d8\u10d9\u10d0)"},{"code":"eu_ES","name":"\u10d1\u10d0\u10e1\u10d9\u10e3\u10e0\u10d8 (\u10d4\u10e1\u10de\u10d0\u10dc\u10d4\u10d7\u10d8)"},{"code":"be_BY","name":"\u10d1\u10d4\u10da\u10dd\u10e0\u10e3\u10e1\u10e3\u10da\u10d8 (\u10d1\u10d4\u10da\u10dd\u10e0\u10e3\u10e1\u10d8\u10d0)"},{"code":"bn_BD","name":"\u10d1\u10d4\u10dc\u10d2\u10d0\u10da\u10e3\u10e0\u10d8 (\u10d1\u10d0\u10dc\u10d2\u10da\u10d0\u10d3\u10d4\u10e8\u10d8)"},{"code":"bn_IN","name":"\u10d1\u10d4\u10dc\u10d2\u10d0\u10da\u10e3\u10e0\u10d8 (\u10d8\u10dc\u10d3\u10dd\u10d4\u10d7\u10d8)"},{"code":"el_CY","name":"\u10d1\u10d4\u10e0\u10eb\u10dc\u10e3\u10da\u10d8 (\u10d9\u10d5\u10d8\u10de\u10e0\u10dd\u10e1\u10d8)"},{"code":"el_GR","name":"\u10d1\u10d4\u10e0\u10eb\u10dc\u10e3\u10da\u10d8 (\u10e1\u10d0\u10d1\u10d4\u10e0\u10eb\u10dc\u10d4\u10d7\u10d8)"},{"code":"my_MM","name":"\u10d1\u10d8\u10e0\u10db\u10e3\u10da\u10d8 (\u10db\u10d8\u10d0\u10dc\u10db\u10d0\u10e0\u10d8 (\u10d1\u10d8\u10e0\u10db\u10d0))"},{"code":"bs_BA","name":"\u10d1\u10dd\u10e1\u10dc\u10d8\u10e3\u10e0\u10d8 (\u10d1\u10dd\u10e1\u10dc\u10d8\u10d0 \u10d3\u10d0 \u10f0\u10d4\u10e0\u10ea\u10d4\u10d2\u10dd\u10d5\u10d8\u10dc\u10d0)"},{"code":"br_FR","name":"\u10d1\u10e0\u10d4\u10e2\u10dd\u10dc\u10e3\u10da\u10d8 (\u10e1\u10d0\u10e4\u10e0\u10d0\u10dc\u10d2\u10d4\u10d7\u10d8)"},{"code":"bg_BG","name":"\u10d1\u10e3\u10da\u10d2\u10d0\u10e0\u10e3\u10da\u10d8 (\u10d1\u10e3\u10da\u10d2\u10d0\u10e0\u10d4\u10d7\u10d8)"},{"code":"gl_ES","name":"\u10d2\u10d0\u10da\u10d8\u10e1\u10d8\u10e3\u10e0\u10d8 (\u10d4\u10e1\u10de\u10d0\u10dc\u10d4\u10d7\u10d8)"},{"code":"lg_UG","name":"\u10d2\u10d0\u10dc\u10d3\u10d0 (\u10e3\u10d2\u10d0\u10dc\u10d3\u10d0)"},{"code":"de_AT","name":"\u10d2\u10d4\u10e0\u10db\u10d0\u10dc\u10e3\u10da\u10d8 (\u10d0\u10d5\u10e1\u10e2\u10e0\u10d8\u10d0)"},{"code":"de_BE","name":"\u10d2\u10d4\u10e0\u10db\u10d0\u10dc\u10e3\u10da\u10d8 (\u10d1\u10d4\u10da\u10d2\u10d8\u10d0)"},{"code":"de_DE","name":"\u10d2\u10d4\u10e0\u10db\u10d0\u10dc\u10e3\u10da\u10d8 (\u10d2\u10d4\u10e0\u10db\u10d0\u10dc\u10d8\u10d0)"},{"code":"de_LI","name":"\u10d2\u10d4\u10e0\u10db\u10d0\u10dc\u10e3\u10da\u10d8 (\u10da\u10d8\u10ee\u10e2\u10d4\u10dc\u10e8\u10e2\u10d4\u10d8\u10dc\u10d8)"},{"code":"de_LU","name":"\u10d2\u10d4\u10e0\u10db\u10d0\u10dc\u10e3\u10da\u10d8 (\u10da\u10e3\u10e5\u10e1\u10d4\u10db\u10d1\u10e3\u10e0\u10d2\u10d8)"},{"code":"de_CH","name":"\u10d2\u10d4\u10e0\u10db\u10d0\u10dc\u10e3\u10da\u10d8 (\u10e8\u10d5\u10d4\u10d8\u10ea\u10d0\u10e0\u10d8\u10d0)"},{"code":"gu_IN","name":"\u10d2\u10e3\u10ef\u10d0\u10e0\u10d0\u10d7\u10d8 (\u10d8\u10dc\u10d3\u10dd\u10d4\u10d7\u10d8)"},{"code":"da_GL","name":"\u10d3\u10d0\u10dc\u10d8\u10e3\u10e0\u10d8 (\u10d2\u10e0\u10d4\u10dc\u10da\u10d0\u10dc\u10d3\u10d8\u10d0)"},{"code":"da_DK","name":"\u10d3\u10d0\u10dc\u10d8\u10e3\u10e0\u10d8 (\u10d3\u10d0\u10dc\u10d8\u10d0)"},{"code":"kl_GL","name":"\u10d3\u10d0\u10e1\u10d0\u10d5\u10da\u10d4\u10d7 \u10d2\u10e0\u10d4\u10dc\u10da\u10d0\u10dc\u10d3\u10d8\u10e3\u10e0\u10d8 (\u10d2\u10e0\u10d4\u10dc\u10da\u10d0\u10dc\u10d3\u10d8\u10d0)"},{"code":"fy_NL","name":"\u10d3\u10d0\u10e1\u10d0\u10d5\u10da\u10d4\u10d7\u10e4\u10e0\u10d8\u10d6\u10d8\u10e3\u10da\u10d8 (\u10dc\u10d8\u10d3\u10d4\u10e0\u10da\u10d0\u10dc\u10d3\u10d4\u10d1\u10d8)"},{"code":"he_IL","name":"\u10d4\u10d1\u10e0\u10d0\u10e3\u10da\u10d8 (\u10d8\u10e1\u10e0\u10d0\u10d4\u10da\u10d8)"},{"code":"ee_GH","name":"\u10d4\u10d5\u10d4 (\u10d2\u10d0\u10dc\u10d0)"},{"code":"ee_TG","name":"\u10d4\u10d5\u10d4 (\u10e2\u10dd\u10d2\u10dd)"},{"code":"es_US","name":"\u10d4\u10e1\u10de\u10d0\u10dc\u10e3\u10e0\u10d8 (\u10d0\u10db\u10d4\u10e0\u10d8\u10d9\u10d8\u10e1 \u10e8\u10d4\u10d4\u10e0\u10d7\u10d4\u10d1\u10e3\u10da\u10d8 \u10e8\u10e2\u10d0\u10e2\u10d4\u10d1\u10d8)"},{"code":"es_AR","name":"\u10d4\u10e1\u10de\u10d0\u10dc\u10e3\u10e0\u10d8 (\u10d0\u10e0\u10d2\u10d4\u10dc\u10e2\u10d8\u10dc\u10d0)"},{"code":"es_BO","name":"\u10d4\u10e1\u10de\u10d0\u10dc\u10e3\u10e0\u10d8 (\u10d1\u10dd\u10da\u10d8\u10d5\u10d8\u10d0)"},{"code":"es_GT","name":"\u10d4\u10e1\u10de\u10d0\u10dc\u10e3\u10e0\u10d8 (\u10d2\u10d5\u10d0\u10e2\u10d4\u10db\u10d0\u10da\u10d0)"},{"code":"es_DO","name":"\u10d4\u10e1\u10de\u10d0\u10dc\u10e3\u10e0\u10d8 (\u10d3\u10dd\u10db\u10d8\u10dc\u10d8\u10d9\u10d0\u10dc\u10d8\u10e1 \u10e0\u10d4\u10e1\u10de\u10e3\u10d1\u10da\u10d8\u10d9\u10d0)"},{"code":"es_EC","name":"\u10d4\u10e1\u10de\u10d0\u10dc\u10e3\u10e0\u10d8 (\u10d4\u10d9\u10d5\u10d0\u10d3\u10dd\u10e0\u10d8)"},{"code":"es_GQ","name":"\u10d4\u10e1\u10de\u10d0\u10dc\u10e3\u10e0\u10d8 (\u10d4\u10d9\u10d5\u10d0\u10e2\u10dd\u10e0\u10e3\u10da\u10d8 \u10d2\u10d5\u10d8\u10dc\u10d4\u10d0)"},{"code":"es_ES","name":"\u10d4\u10e1\u10de\u10d0\u10dc\u10e3\u10e0\u10d8 (\u10d4\u10e1\u10de\u10d0\u10dc\u10d4\u10d7\u10d8)"},{"code":"es_VE","name":"\u10d4\u10e1\u10de\u10d0\u10dc\u10e3\u10e0\u10d8 (\u10d5\u10d4\u10dc\u10d4\u10e1\u10e3\u10d4\u10da\u10d0)"},{"code":"es_IC","name":"\u10d4\u10e1\u10de\u10d0\u10dc\u10e3\u10e0\u10d8 (\u10d9\u10d0\u10dc\u10d0\u10e0\u10d8\u10e1 \u10d9\u10e3\u10dc\u10eb\u10e3\u10da\u10d4\u10d1\u10d8)"},{"code":"es_CO","name":"\u10d4\u10e1\u10de\u10d0\u10dc\u10e3\u10e0\u10d8 (\u10d9\u10dd\u10da\u10e3\u10db\u10d1\u10d8\u10d0)"},{"code":"es_CR","name":"\u10d4\u10e1\u10de\u10d0\u10dc\u10e3\u10e0\u10d8 (\u10d9\u10dd\u10e1\u10e2\u10d0-\u10e0\u10d8\u10d9\u10d0)"},{"code":"es_CU","name":"\u10d4\u10e1\u10de\u10d0\u10dc\u10e3\u10e0\u10d8 (\u10d9\u10e3\u10d1\u10d0)"},{"code":"es_MX","name":"\u10d4\u10e1\u10de\u10d0\u10dc\u10e3\u10e0\u10d8 (\u10db\u10d4\u10e5\u10e1\u10d8\u10d9\u10d0)"},{"code":"es_NI","name":"\u10d4\u10e1\u10de\u10d0\u10dc\u10e3\u10e0\u10d8 (\u10dc\u10d8\u10d9\u10d0\u10e0\u10d0\u10d2\u10e3\u10d0)"},{"code":"es_PA","name":"\u10d4\u10e1\u10de\u10d0\u10dc\u10e3\u10e0\u10d8 (\u10de\u10d0\u10dc\u10d0\u10db\u10d0)"},{"code":"es_PY","name":"\u10d4\u10e1\u10de\u10d0\u10dc\u10e3\u10e0\u10d8 (\u10de\u10d0\u10e0\u10d0\u10d2\u10d5\u10d0\u10d8)"},{"code":"es_PE","name":"\u10d4\u10e1\u10de\u10d0\u10dc\u10e3\u10e0\u10d8 (\u10de\u10d4\u10e0\u10e3)"},{"code":"es_PR","name":"\u10d4\u10e1\u10de\u10d0\u10dc\u10e3\u10e0\u10d8 (\u10de\u10e3\u10d4\u10e0\u10e2\u10dd-\u10e0\u10d8\u10d9\u10dd)"},{"code":"es_SV","name":"\u10d4\u10e1\u10de\u10d0\u10dc\u10e3\u10e0\u10d8 (\u10e1\u10d0\u10da\u10d5\u10d0\u10d3\u10dd\u10e0\u10d8)"},{"code":"es_EA","name":"\u10d4\u10e1\u10de\u10d0\u10dc\u10e3\u10e0\u10d8 (\u10e1\u10d4\u10e3\u10e2\u10d0 \u10d3\u10d0 \u10db\u10d4\u10da\u10d8\u10da\u10d0)"},{"code":"es_UY","name":"\u10d4\u10e1\u10de\u10d0\u10dc\u10e3\u10e0\u10d8 (\u10e3\u10e0\u10e3\u10d2\u10d5\u10d0\u10d8)"},{"code":"es_PH","name":"\u10d4\u10e1\u10de\u10d0\u10dc\u10e3\u10e0\u10d8 (\u10e4\u10d8\u10da\u10d8\u10de\u10d8\u10dc\u10d4\u10d1\u10d8)"},{"code":"es_CL","name":"\u10d4\u10e1\u10de\u10d0\u10dc\u10e3\u10e0\u10d8 (\u10e9\u10d8\u10da\u10d4)"},{"code":"es_HN","name":"\u10d4\u10e1\u10de\u10d0\u10dc\u10e3\u10e0\u10d8 (\u10f0\u10dd\u10dc\u10d3\u10e3\u10e0\u10d0\u10e1\u10d8)"},{"code":"et_EE","name":"\u10d4\u10e1\u10e2\u10dd\u10dc\u10e3\u10e0\u10d8 (\u10d4\u10e1\u10e2\u10dd\u10dc\u10d4\u10d7\u10d8)"},{"code":"vi_VN","name":"\u10d5\u10d8\u10d4\u10e2\u10dc\u10d0\u10db\u10e3\u10e0\u10d8 (\u10d5\u10d8\u10d4\u10e2\u10dc\u10d0\u10db\u10d8)"},{"code":"zu_ZA","name":"\u10d6\u10e3\u10da\u10e3 (\u10e1\u10d0\u10db\u10ee\u10e0\u10d4\u10d7 \u10d0\u10e4\u10e0\u10d8\u10d9\u10d0)"},{"code":"ti_ET","name":"\u10d7\u10d8\u10d2\u10e0\u10d8\u10dc\u10d8\u10d0 (\u10d4\u10d7\u10d8\u10dd\u10de\u10d8\u10d0)"},{"code":"ti_ER","name":"\u10d7\u10d8\u10d2\u10e0\u10d8\u10dc\u10d8\u10d0 (\u10d4\u10e0\u10d8\u10e2\u10e0\u10d4\u10d0)"},{"code":"tr_TR","name":"\u10d7\u10e3\u10e0\u10e5\u10e3\u10da\u10d8 (\u10d7\u10e3\u10e0\u10e5\u10d4\u10d7\u10d8)"},{"code":"tr_CY","name":"\u10d7\u10e3\u10e0\u10e5\u10e3\u10da\u10d8 (\u10d9\u10d5\u10d8\u10de\u10e0\u10dd\u10e1\u10d8)"},{"code":"ja_JP","name":"\u10d8\u10d0\u10de\u10dd\u10dc\u10e3\u10e0\u10d8 (\u10d8\u10d0\u10de\u10dd\u10dc\u10d8\u10d0)"},{"code":"ig_NG","name":"\u10d8\u10d2\u10d1\u10dd (\u10dc\u10d8\u10d2\u10d4\u10e0\u10d8\u10d0)"},{"code":"en_AU","name":"\u10d8\u10dc\u10d2\u10da\u10d8\u10e1\u10e3\u10e0\u10d8 (\u10d0\u10d5\u10e1\u10e2\u10e0\u10d0\u10da\u10d8\u10d0)"},{"code":"en_US","name":"\u10d8\u10dc\u10d2\u10da\u10d8\u10e1\u10e3\u10e0\u10d8 (\u10d0\u10db\u10d4\u10e0\u10d8\u10d9\u10d8\u10e1 \u10e8\u10d4\u10d4\u10e0\u10d7\u10d4\u10d1\u10e3\u10da\u10d8 \u10e8\u10e2\u10d0\u10e2\u10d4\u10d1\u10d8)"},{"code":"en_AS","name":"\u10d8\u10dc\u10d2\u10da\u10d8\u10e1\u10e3\u10e0\u10d8 (\u10d0\u10db\u10d4\u10e0\u10d8\u10d9\u10e3\u10da\u10d8 \u10e1\u10d0\u10db\u10dd\u10d0)"},{"code":"en_AI","name":"\u10d8\u10dc\u10d2\u10da\u10d8\u10e1\u10e3\u10e0\u10d8 (\u10d0\u10dc\u10d2\u10d5\u10d8\u10da\u10d0)"},{"code":"en_AG","name":"\u10d8\u10dc\u10d2\u10da\u10d8\u10e1\u10e3\u10e0\u10d8 (\u10d0\u10dc\u10e2\u10d8\u10d2\u10e3\u10d0 \u10d3\u10d0 \u10d1\u10d0\u10e0\u10d1\u10e3\u10d3\u10d0)"},{"code":"en_VI","name":"\u10d8\u10dc\u10d2\u10da\u10d8\u10e1\u10e3\u10e0\u10d8 (\u10d0\u10e8\u10e8-\u10d8\u10e1 \u10d5\u10d8\u10e0\u10ef\u10d8\u10dc\u10d8\u10d8\u10e1 \u10d9\u10e3\u10dc\u10eb\u10e3\u10da\u10d4\u10d1\u10d8)"},{"code":"en_UM","name":"\u10d8\u10dc\u10d2\u10da\u10d8\u10e1\u10e3\u10e0\u10d8 (\u10d0\u10e8\u10e8-\u10d8\u10e1 \u10e8\u10dd\u10e0\u10d4\u10e3\u10da\u10d8 \u10d9\u10e3\u10dc\u10eb\u10e3\u10da\u10d4\u10d1\u10d8)"},{"code":"en_NZ","name":"\u10d8\u10dc\u10d2\u10da\u10d8\u10e1\u10e3\u10e0\u10d8 (\u10d0\u10ee\u10d0\u10da\u10d8 \u10d6\u10d4\u10da\u10d0\u10dc\u10d3\u10d8\u10d0)"},{"code":"en_BB","name":"\u10d8\u10dc\u10d2\u10da\u10d8\u10e1\u10e3\u10e0\u10d8 (\u10d1\u10d0\u10e0\u10d1\u10d0\u10d3\u10dd\u10e1\u10d8)"},{"code":"en_BS","name":"\u10d8\u10dc\u10d2\u10da\u10d8\u10e1\u10e3\u10e0\u10d8 (\u10d1\u10d0\u10f0\u10d0\u10db\u10d8\u10e1 \u10d9\u10e3\u10dc\u10eb\u10e3\u10da\u10d4\u10d1\u10d8)"},{"code":"en_BE","name":"\u10d8\u10dc\u10d2\u10da\u10d8\u10e1\u10e3\u10e0\u10d8 (\u10d1\u10d4\u10da\u10d2\u10d8\u10d0)"},{"code":"en_BZ","name":"\u10d8\u10dc\u10d2\u10da\u10d8\u10e1\u10e3\u10e0\u10d8 (\u10d1\u10d4\u10da\u10d8\u10d6\u10d8)"},{"code":"en_BM","name":"\u10d8\u10dc\u10d2\u10da\u10d8\u10e1\u10e3\u10e0\u10d8 (\u10d1\u10d4\u10e0\u10db\u10e3\u10d3\u10d8)"},{"code":"en_BW","name":"\u10d8\u10dc\u10d2\u10da\u10d8\u10e1\u10e3\u10e0\u10d8 (\u10d1\u10dd\u10e2\u10e1\u10d5\u10d0\u10dc\u10d0)"},{"code":"en_VG","name":"\u10d8\u10dc\u10d2\u10da\u10d8\u10e1\u10e3\u10e0\u10d8 (\u10d1\u10e0\u10d8\u10e2\u10d0\u10dc\u10d4\u10d7\u10d8\u10e1 \u10d5\u10d8\u10e0\u10ef\u10d8\u10dc\u10d8\u10d8\u10e1 \u10d9\u10e3\u10dc\u10eb\u10e3\u10da\u10d4\u10d1\u10d8)"},{"code":"en_IO","name":"\u10d8\u10dc\u10d2\u10da\u10d8\u10e1\u10e3\u10e0\u10d8 (\u10d1\u10e0\u10d8\u10e2\u10d0\u10dc\u10e3\u10da\u10d8 \u10e2\u10d4\u10e0\u10d8\u10e2\u10dd\u10e0\u10d8\u10d0 \u10d8\u10dc\u10d3\u10dd\u10d4\u10d7\u10d8\u10e1 \u10dd\u10d9\u10d4\u10d0\u10dc\u10d4\u10e8\u10d8)"},{"code":"en_GY","name":"\u10d8\u10dc\u10d2\u10da\u10d8\u10e1\u10e3\u10e0\u10d8 (\u10d2\u10d0\u10d8\u10d0\u10dc\u10d0)"},{"code":"en_GM","name":"\u10d8\u10dc\u10d2\u10da\u10d8\u10e1\u10e3\u10e0\u10d8 (\u10d2\u10d0\u10db\u10d1\u10d8\u10d0)"},{"code":"en_GH","name":"\u10d8\u10dc\u10d2\u10da\u10d8\u10e1\u10e3\u10e0\u10d8 (\u10d2\u10d0\u10dc\u10d0)"},{"code":"en_GG","name":"\u10d8\u10dc\u10d2\u10da\u10d8\u10e1\u10e3\u10e0\u10d8 (\u10d2\u10d4\u10e0\u10dc\u10e1\u10d8)"},{"code":"en_GI","name":"\u10d8\u10dc\u10d2\u10da\u10d8\u10e1\u10e3\u10e0\u10d8 (\u10d2\u10d8\u10d1\u10e0\u10d0\u10da\u10e2\u10d0\u10e0\u10d8)"},{"code":"en_GD","name":"\u10d8\u10dc\u10d2\u10da\u10d8\u10e1\u10e3\u10e0\u10d8 (\u10d2\u10e0\u10d4\u10dc\u10d0\u10d3\u10d0)"},{"code":"en_GU","name":"\u10d8\u10dc\u10d2\u10da\u10d8\u10e1\u10e3\u10e0\u10d8 (\u10d2\u10e3\u10d0\u10db\u10d8)"},{"code":"en_GB","name":"\u10d8\u10dc\u10d2\u10da\u10d8\u10e1\u10e3\u10e0\u10d8 (\u10d3\u10d8\u10d3\u10d8 \u10d1\u10e0\u10d8\u10e2\u10d0\u10dc\u10d4\u10d7\u10d8)"},{"code":"en_DG","name":"\u10d8\u10dc\u10d2\u10da\u10d8\u10e1\u10e3\u10e0\u10d8 (\u10d3\u10d8\u10d4\u10d2\u10dd-\u10d2\u10d0\u10e0\u10e1\u10d8\u10d0)"},{"code":"en_DM","name":"\u10d8\u10dc\u10d2\u10da\u10d8\u10e1\u10e3\u10e0\u10d8 (\u10d3\u10dd\u10db\u10d8\u10dc\u10d8\u10d9\u10d0)"},{"code":"en_ER","name":"\u10d8\u10dc\u10d2\u10da\u10d8\u10e1\u10e3\u10e0\u10d8 (\u10d4\u10e0\u10d8\u10e2\u10e0\u10d4\u10d0)"},{"code":"en_VU","name":"\u10d8\u10dc\u10d2\u10da\u10d8\u10e1\u10e3\u10e0\u10d8 (\u10d5\u10d0\u10dc\u10e3\u10d0\u10e2\u10e3)"},{"code":"en_ZM","name":"\u10d8\u10dc\u10d2\u10da\u10d8\u10e1\u10e3\u10e0\u10d8 (\u10d6\u10d0\u10db\u10d1\u10d8\u10d0)"},{"code":"en_ZW","name":"\u10d8\u10dc\u10d2\u10da\u10d8\u10e1\u10e3\u10e0\u10d8 (\u10d6\u10d8\u10db\u10d1\u10d0\u10d1\u10d5\u10d4)"},{"code":"en_JM","name":"\u10d8\u10dc\u10d2\u10da\u10d8\u10e1\u10e3\u10e0\u10d8 (\u10d8\u10d0\u10db\u10d0\u10d8\u10d9\u10d0)"},{"code":"en_IN","name":"\u10d8\u10dc\u10d2\u10da\u10d8\u10e1\u10e3\u10e0\u10d8 (\u10d8\u10dc\u10d3\u10dd\u10d4\u10d7\u10d8)"},{"code":"en_IE","name":"\u10d8\u10dc\u10d2\u10da\u10d8\u10e1\u10e3\u10e0\u10d8 (\u10d8\u10e0\u10da\u10d0\u10dc\u10d3\u10d8\u10d0)"},{"code":"en_KY","name":"\u10d8\u10dc\u10d2\u10da\u10d8\u10e1\u10e3\u10e0\u10d8 (\u10d9\u10d0\u10d8\u10db\u10d0\u10dc\u10d8\u10e1 \u10d9\u10e3\u10dc\u10eb\u10e3\u10da\u10d4\u10d1\u10d8)"},{"code":"en_CM","name":"\u10d8\u10dc\u10d2\u10da\u10d8\u10e1\u10e3\u10e0\u10d8 (\u10d9\u10d0\u10db\u10d4\u10e0\u10e3\u10dc\u10d8)"},{"code":"en_CA","name":"\u10d8\u10dc\u10d2\u10da\u10d8\u10e1\u10e3\u10e0\u10d8 (\u10d9\u10d0\u10dc\u10d0\u10d3\u10d0)"},{"code":"en_KE","name":"\u10d8\u10dc\u10d2\u10da\u10d8\u10e1\u10e3\u10e0\u10d8 (\u10d9\u10d4\u10dc\u10d8\u10d0)"},{"code":"en_KI","name":"\u10d8\u10dc\u10d2\u10da\u10d8\u10e1\u10e3\u10e0\u10d8 (\u10d9\u10d8\u10e0\u10d8\u10d1\u10d0\u10e2\u10d8)"},{"code":"en_CK","name":"\u10d8\u10dc\u10d2\u10da\u10d8\u10e1\u10e3\u10e0\u10d8 (\u10d9\u10e3\u10d9\u10d8\u10e1 \u10d9\u10e3\u10dc\u10eb\u10e3\u10da\u10d4\u10d1\u10d8)"},{"code":"en_LS","name":"\u10d8\u10dc\u10d2\u10da\u10d8\u10e1\u10e3\u10e0\u10d8 (\u10da\u10d4\u10e1\u10dd\u10d7\u10dd)"},{"code":"en_LR","name":"\u10d8\u10dc\u10d2\u10da\u10d8\u10e1\u10e3\u10e0\u10d8 (\u10da\u10d8\u10d1\u10d4\u10e0\u10d8\u10d0)"},{"code":"en_MG","name":"\u10d8\u10dc\u10d2\u10da\u10d8\u10e1\u10e3\u10e0\u10d8 (\u10db\u10d0\u10d3\u10d0\u10d2\u10d0\u10e1\u10d9\u10d0\u10e0\u10d8)"},{"code":"en_MU","name":"\u10d8\u10dc\u10d2\u10da\u10d8\u10e1\u10e3\u10e0\u10d8 (\u10db\u10d0\u10d5\u10e0\u10d8\u10d9\u10d8)"},{"code":"en_MO","name":"\u10d8\u10dc\u10d2\u10da\u10d8\u10e1\u10e3\u10e0\u10d8 (\u10db\u10d0\u10d9\u10d0\u10dd\u10e1 \u10e1\u10de\u10d4\u10ea\u10d8\u10d0\u10da\u10e3\u10e0\u10d8 \u10d0\u10d3\u10db\u10d8\u10dc\u10d8\u10e1\u10e2\u10e0\u10d0\u10ea\u10d8\u10e3\u10da\u10d8 \u10e0\u10d4\u10d2\u10d8\u10dd\u10dc\u10d8 \u10e9\u10d8\u10dc\u10d4\u10d7\u10d8)"},{"code":"en_MW","name":"\u10d8\u10dc\u10d2\u10da\u10d8\u10e1\u10e3\u10e0\u10d8 (\u10db\u10d0\u10da\u10d0\u10d5\u10d8)"},{"code":"en_MY","name":"\u10d8\u10dc\u10d2\u10da\u10d8\u10e1\u10e3\u10e0\u10d8 (\u10db\u10d0\u10da\u10d0\u10d8\u10d6\u10d8\u10d0)"},{"code":"en_MT","name":"\u10d8\u10dc\u10d2\u10da\u10d8\u10e1\u10e3\u10e0\u10d8 (\u10db\u10d0\u10da\u10e2\u10d0)"},{"code":"en_MH","name":"\u10d8\u10dc\u10d2\u10da\u10d8\u10e1\u10e3\u10e0\u10d8 (\u10db\u10d0\u10e0\u10e8\u10d0\u10da\u10d8\u10e1 \u10d9\u10e3\u10dc\u10eb\u10e3\u10da\u10d4\u10d1\u10d8)"},{"code":"en_IM","name":"\u10d8\u10dc\u10d2\u10da\u10d8\u10e1\u10e3\u10e0\u10d8 (\u10db\u10d4\u10dc\u10d8\u10e1 \u10d9\u10e3\u10dc\u10eb\u10e3\u10da\u10d8)"},{"code":"en_FM","name":"\u10d8\u10dc\u10d2\u10da\u10d8\u10e1\u10e3\u10e0\u10d8 (\u10db\u10d8\u10d9\u10e0\u10dd\u10dc\u10d4\u10d6\u10d8\u10d0)"},{"code":"en_MS","name":"\u10d8\u10dc\u10d2\u10da\u10d8\u10e1\u10e3\u10e0\u10d8 (\u10db\u10dd\u10dc\u10e1\u10d4\u10e0\u10d0\u10e2\u10d8)"},{"code":"en_NA","name":"\u10d8\u10dc\u10d2\u10da\u10d8\u10e1\u10e3\u10e0\u10d8 (\u10dc\u10d0\u10db\u10d8\u10d1\u10d8\u10d0)"},{"code":"en_NR","name":"\u10d8\u10dc\u10d2\u10da\u10d8\u10e1\u10e3\u10e0\u10d8 (\u10dc\u10d0\u10e3\u10e0\u10e3)"},{"code":"en_NG","name":"\u10d8\u10dc\u10d2\u10da\u10d8\u10e1\u10e3\u10e0\u10d8 (\u10dc\u10d8\u10d2\u10d4\u10e0\u10d8\u10d0)"},{"code":"en_NU","name":"\u10d8\u10dc\u10d2\u10da\u10d8\u10e1\u10e3\u10e0\u10d8 (\u10dc\u10d8\u10e3\u10d4)"},{"code":"en_NF","name":"\u10d8\u10dc\u10d2\u10da\u10d8\u10e1\u10e3\u10e0\u10d8 (\u10dc\u10dd\u10e0\u10e4\u10dd\u10da\u10d9\u10d8\u10e1 \u10d9\u10e3\u10dc\u10eb\u10e3\u10da\u10d8)"},{"code":"en_PK","name":"\u10d8\u10dc\u10d2\u10da\u10d8\u10e1\u10e3\u10e0\u10d8 (\u10de\u10d0\u10d9\u10d8\u10e1\u10e2\u10d0\u10dc\u10d8)"},{"code":"en_PW","name":"\u10d8\u10dc\u10d2\u10da\u10d8\u10e1\u10e3\u10e0\u10d8 (\u10de\u10d0\u10da\u10d0\u10e3)"},{"code":"en_PG","name":"\u10d8\u10dc\u10d2\u10da\u10d8\u10e1\u10e3\u10e0\u10d8 (\u10de\u10d0\u10de\u10e3\u10d0-\u10d0\u10ee\u10d0\u10da\u10d8 \u10d2\u10d5\u10d8\u10dc\u10d4\u10d0)"},{"code":"en_PN","name":"\u10d8\u10dc\u10d2\u10da\u10d8\u10e1\u10e3\u10e0\u10d8 (\u10de\u10d8\u10e2\u10d9\u10d4\u10e0\u10dc\u10d8\u10e1 \u10d9\u10e3\u10dc\u10eb\u10e3\u10da\u10d4\u10d1\u10d8)"},{"code":"en_PR","name":"\u10d8\u10dc\u10d2\u10da\u10d8\u10e1\u10e3\u10e0\u10d8 (\u10de\u10e3\u10d4\u10e0\u10e2\u10dd-\u10e0\u10d8\u10d9\u10dd)"},{"code":"en_RW","name":"\u10d8\u10dc\u10d2\u10da\u10d8\u10e1\u10e3\u10e0\u10d8 (\u10e0\u10e3\u10d0\u10dc\u10d3\u10d0)"},{"code":"en_WS","name":"\u10d8\u10dc\u10d2\u10da\u10d8\u10e1\u10e3\u10e0\u10d8 (\u10e1\u10d0\u10db\u10dd\u10d0)"},{"code":"en_ZA","name":"\u10d8\u10dc\u10d2\u10da\u10d8\u10e1\u10e3\u10e0\u10d8 (\u10e1\u10d0\u10db\u10ee\u10e0\u10d4\u10d7 \u10d0\u10e4\u10e0\u10d8\u10d9\u10d0)"},{"code":"en_SS","name":"\u10d8\u10dc\u10d2\u10da\u10d8\u10e1\u10e3\u10e0\u10d8 (\u10e1\u10d0\u10db\u10ee\u10e0\u10d4\u10d7\u10d8 \u10e1\u10e3\u10d3\u10d0\u10dc\u10d8)"},{"code":"en_SC","name":"\u10d8\u10dc\u10d2\u10da\u10d8\u10e1\u10e3\u10e0\u10d8 (\u10e1\u10d4\u10d8\u10e8\u10d4\u10da\u10d8\u10e1 \u10d9\u10e3\u10dc\u10eb\u10e3\u10da\u10d4\u10d1\u10d8)"},{"code":"en_VC","name":"\u10d8\u10dc\u10d2\u10da\u10d8\u10e1\u10e3\u10e0\u10d8 (\u10e1\u10d4\u10dc\u10e2-\u10d5\u10d8\u10dc\u10e1\u10d4\u10dc\u10e2\u10d8 \u10d3\u10d0 \u10d2\u10e0\u10d4\u10dc\u10d0\u10d3\u10d8\u10dc\u10d4\u10d1\u10d8)"},{"code":"en_KN","name":"\u10d8\u10dc\u10d2\u10da\u10d8\u10e1\u10e3\u10e0\u10d8 (\u10e1\u10d4\u10dc\u10e2-\u10d9\u10d8\u10e2\u10e1\u10d8 \u10d3\u10d0 \u10dc\u10d4\u10d5\u10d8\u10e1\u10d8)"},{"code":"en_LC","name":"\u10d8\u10dc\u10d2\u10da\u10d8\u10e1\u10e3\u10e0\u10d8 (\u10e1\u10d4\u10dc\u10e2-\u10da\u10e3\u10e1\u10d8\u10d0)"},{"code":"en_SZ","name":"\u10d8\u10dc\u10d2\u10da\u10d8\u10e1\u10e3\u10e0\u10d8 (\u10e1\u10d5\u10d0\u10d6\u10d8\u10da\u10d4\u10dc\u10d3\u10d8)"},{"code":"en_SL","name":"\u10d8\u10dc\u10d2\u10da\u10d8\u10e1\u10e3\u10e0\u10d8 (\u10e1\u10d8\u10d4\u10e0\u10d0-\u10da\u10d4\u10dd\u10dc\u10d4)"},{"code":"en_SG","name":"\u10d8\u10dc\u10d2\u10da\u10d8\u10e1\u10e3\u10e0\u10d8 (\u10e1\u10d8\u10dc\u10d2\u10d0\u10de\u10e3\u10e0\u10d8)"},{"code":"en_SX","name":"\u10d8\u10dc\u10d2\u10da\u10d8\u10e1\u10e3\u10e0\u10d8 (\u10e1\u10d8\u10dc\u10e2-\u10db\u10d0\u10e0\u10e2\u10d4\u10dc\u10d8)"},{"code":"en_SB","name":"\u10d8\u10dc\u10d2\u10da\u10d8\u10e1\u10e3\u10e0\u10d8 (\u10e1\u10dd\u10da\u10dd\u10db\u10dd\u10dc\u10d8\u10e1 \u10d9\u10e3\u10dc\u10eb\u10e3\u10da\u10d4\u10d1\u10d8)"},{"code":"en_SD","name":"\u10d8\u10dc\u10d2\u10da\u10d8\u10e1\u10e3\u10e0\u10d8 (\u10e1\u10e3\u10d3\u10d0\u10dc\u10d8)"},{"code":"en_TZ","name":"\u10d8\u10dc\u10d2\u10da\u10d8\u10e1\u10e3\u10e0\u10d8 (\u10e2\u10d0\u10dc\u10d6\u10d0\u10dc\u10d8\u10d0)"},{"code":"en_TC","name":"\u10d8\u10dc\u10d2\u10da\u10d8\u10e1\u10e3\u10e0\u10d8 (\u10e2\u10d4\u10e0\u10d9\u10e1\u10d8\u10e1 \u10d3\u10d0 \u10d9\u10d0\u10d8\u10d9\u10dd\u10e1\u10d8\u10e1 \u10d9\u10e3\u10dc\u10eb\u10e3\u10da\u10d4\u10d1\u10d8)"},{"code":"en_TK","name":"\u10d8\u10dc\u10d2\u10da\u10d8\u10e1\u10e3\u10e0\u10d8 (\u10e2\u10dd\u10d9\u10d4\u10da\u10d0\u10e3)"},{"code":"en_TO","name":"\u10d8\u10dc\u10d2\u10da\u10d8\u10e1\u10e3\u10e0\u10d8 (\u10e2\u10dd\u10dc\u10d2\u10d0)"},{"code":"en_TT","name":"\u10d8\u10dc\u10d2\u10da\u10d8\u10e1\u10e3\u10e0\u10d8 (\u10e2\u10e0\u10d8\u10dc\u10d8\u10d3\u10d0\u10d3\u10d8 \u10d3\u10d0 \u10e2\u10dd\u10d1\u10d0\u10d2\u10dd)"},{"code":"en_TV","name":"\u10d8\u10dc\u10d2\u10da\u10d8\u10e1\u10e3\u10e0\u10d8 (\u10e2\u10e3\u10d5\u10d0\u10da\u10e3)"},{"code":"en_UG","name":"\u10d8\u10dc\u10d2\u10da\u10d8\u10e1\u10e3\u10e0\u10d8 (\u10e3\u10d2\u10d0\u10dc\u10d3\u10d0)"},{"code":"en_PH","name":"\u10d8\u10dc\u10d2\u10da\u10d8\u10e1\u10e3\u10e0\u10d8 (\u10e4\u10d8\u10da\u10d8\u10de\u10d8\u10dc\u10d4\u10d1\u10d8)"},{"code":"en_FJ","name":"\u10d8\u10dc\u10d2\u10da\u10d8\u10e1\u10e3\u10e0\u10d8 (\u10e4\u10d8\u10ef\u10d8)"},{"code":"en_FK","name":"\u10d8\u10dc\u10d2\u10da\u10d8\u10e1\u10e3\u10e0\u10d8 (\u10e4\u10dd\u10da\u10d9\u10da\u10d4\u10dc\u10d3\u10d8\u10e1 \u10d9\u10e3\u10dc\u10eb\u10e3\u10da\u10d4\u10d1\u10d8)"},{"code":"en_CC","name":"\u10d8\u10dc\u10d2\u10da\u10d8\u10e1\u10e3\u10e0\u10d8 (\u10e5\u10dd\u10e5\u10dd\u10e1\u10d8\u10e1 (\u10d9\u10d8\u10da\u10d8\u10dc\u10d2\u10d8\u10e1) \u10d9\u10e3\u10dc\u10eb\u10e3\u10da\u10d4\u10d1\u10d8)"},{"code":"en_CX","name":"\u10d8\u10dc\u10d2\u10da\u10d8\u10e1\u10e3\u10e0\u10d8 (\u10e8\u10dd\u10d1\u10d8\u10e1 \u10d9\u10e3\u10dc\u10eb\u10e3\u10da\u10d8)"},{"code":"en_MP","name":"\u10d8\u10dc\u10d2\u10da\u10d8\u10e1\u10e3\u10e0\u10d8 (\u10e9\u10e0\u10d3\u10d8\u10da\u10dd\u10d4\u10d7 \u10db\u10d0\u10e0\u10d8\u10d0\u10dc\u10d0\u10e1 \u10d9\u10e3\u10dc\u10eb\u10e3\u10da\u10d4\u10d1\u10d8)"},{"code":"en_SH","name":"\u10d8\u10dc\u10d2\u10da\u10d8\u10e1\u10e3\u10e0\u10d8 (\u10ec\u10db\u10d8\u10dc\u10d3\u10d0 \u10d4\u10da\u10d4\u10dc\u10d4\u10e1 \u10d9\u10e3\u10dc\u10eb\u10e3\u10da\u10d8)"},{"code":"en_JE","name":"\u10d8\u10dc\u10d2\u10da\u10d8\u10e1\u10e3\u10e0\u10d8 (\u10ef\u10d4\u10e0\u10e1\u10d8)"},{"code":"en_HK","name":"\u10d8\u10dc\u10d2\u10da\u10d8\u10e1\u10e3\u10e0\u10d8 (\u10f0\u10dd\u10dc\u10d9\u10dd\u10dc\u10d2\u10d8\u10e1 \u10e1\u10de\u10d4\u10ea\u10d8\u10d0\u10da\u10e3\u10e0\u10d8 \u10d0\u10d3\u10db\u10d8\u10dc\u10d8\u10e1\u10e2\u10e0\u10d0\u10ea\u10d8\u10e3\u10da\u10d8 \u10e0\u10d4\u10d2\u10d8\u10dd\u10dc\u10d8 \u10e9\u10d8\u10dc\u10d4\u10d7\u10d8)"},{"code":"id_ID","name":"\u10d8\u10dc\u10d3\u10dd\u10dc\u10d4\u10d6\u10d8\u10e3\u10e0\u10d8 (\u10d8\u10dc\u10d3\u10dd\u10dc\u10d4\u10d6\u10d8\u10d0)"},{"code":"yo_BJ","name":"\u10d8\u10dd\u10e0\u10e3\u10d1\u10d0 (\u10d1\u10d4\u10dc\u10d8\u10dc\u10d8)"},{"code":"yo_NG","name":"\u10d8\u10dd\u10e0\u10e3\u10d1\u10d0 (\u10dc\u10d8\u10d2\u10d4\u10e0\u10d8\u10d0)"},{"code":"ga_IE","name":"\u10d8\u10e0\u10da\u10d0\u10dc\u10d3\u10d8\u10e3\u10e0\u10d8 (\u10d8\u10e0\u10da\u10d0\u10dc\u10d3\u10d8\u10d0)"},{"code":"is_IS","name":"\u10d8\u10e1\u10da\u10d0\u10dc\u10d3\u10d8\u10e3\u10e0\u10d8 (\u10d8\u10e1\u10da\u10d0\u10dc\u10d3\u10d8\u10d0)"},{"code":"it_IT","name":"\u10d8\u10e2\u10d0\u10da\u10d8\u10e3\u10e0\u10d8 (\u10d8\u10e2\u10d0\u10da\u10d8\u10d0)"},{"code":"it_SM","name":"\u10d8\u10e2\u10d0\u10da\u10d8\u10e3\u10e0\u10d8 (\u10e1\u10d0\u10dc-\u10db\u10d0\u10e0\u10d8\u10dc\u10dd)"},{"code":"it_CH","name":"\u10d8\u10e2\u10d0\u10da\u10d8\u10e3\u10e0\u10d8 (\u10e8\u10d5\u10d4\u10d8\u10ea\u10d0\u10e0\u10d8\u10d0)"},{"code":"kn_IN","name":"\u10d9\u10d0\u10dc\u10d0\u10d3\u10d0 (\u10d8\u10dc\u10d3\u10dd\u10d4\u10d7\u10d8)"},{"code":"ca_AD","name":"\u10d9\u10d0\u10e2\u10d0\u10da\u10d0\u10dc\u10e3\u10e0\u10d8 (\u10d0\u10dc\u10d3\u10dd\u10e0\u10d0)"},{"code":"ca_ES","name":"\u10d9\u10d0\u10e2\u10d0\u10da\u10d0\u10dc\u10e3\u10e0\u10d8 (\u10d4\u10e1\u10de\u10d0\u10dc\u10d4\u10d7\u10d8)"},{"code":"ca_IT","name":"\u10d9\u10d0\u10e2\u10d0\u10da\u10d0\u10dc\u10e3\u10e0\u10d8 (\u10d8\u10e2\u10d0\u10da\u10d8\u10d0)"},{"code":"ca_FR","name":"\u10d9\u10d0\u10e2\u10d0\u10da\u10d0\u10dc\u10e3\u10e0\u10d8 (\u10e1\u10d0\u10e4\u10e0\u10d0\u10dc\u10d2\u10d4\u10d7\u10d8)"},{"code":"qu_BO","name":"\u10d9\u10d4\u10e9\u10e3\u10d0 (\u10d1\u10dd\u10da\u10d8\u10d5\u10d8\u10d0)"},{"code":"qu_EC","name":"\u10d9\u10d4\u10e9\u10e3\u10d0 (\u10d4\u10d9\u10d5\u10d0\u10d3\u10dd\u10e0\u10d8)"},{"code":"qu_PE","name":"\u10d9\u10d4\u10e9\u10e3\u10d0 (\u10de\u10d4\u10e0\u10e3)"},{"code":"ki_KE","name":"\u10d9\u10d8\u10d9\u10e3\u10d8\u10e3 (\u10d9\u10d4\u10dc\u10d8\u10d0)"},{"code":"rw_RW","name":"\u10d9\u10d8\u10dc\u10d8\u10d0\u10e0\u10e3\u10d0\u10dc\u10d3\u10d0 (\u10e0\u10e3\u10d0\u10dc\u10d3\u10d0)"},{"code":"ko_KR","name":"\u10d9\u10dd\u10e0\u10d4\u10e3\u10da\u10d8 (\u10e1\u10d0\u10db\u10ee\u10e0\u10d4\u10d7\u10d8 \u10d9\u10dd\u10e0\u10d4\u10d0)"},{"code":"ko_KP","name":"\u10d9\u10dd\u10e0\u10d4\u10e3\u10da\u10d8 (\u10e9\u10e0\u10d3\u10d8\u10da\u10dd\u10d4\u10d7\u10d8 \u10d9\u10dd\u10e0\u10d4\u10d0)"},{"code":"kw_GB","name":"\u10d9\u10dd\u10e0\u10dc\u10e3\u10da\u10d8 (\u10d3\u10d8\u10d3\u10d8 \u10d1\u10e0\u10d8\u10e2\u10d0\u10dc\u10d4\u10d7\u10d8)"},{"code":"lo_LA","name":"\u10da\u10d0\u10dd\u10e1\u10e3\u10e0\u10d8 (\u10da\u10d0\u10dd\u10e1\u10d8)"},{"code":"lv_LV","name":"\u10da\u10d0\u10e2\u10d5\u10d8\u10e3\u10e0\u10d8 (\u10da\u10d0\u10e2\u10d5\u10d8\u10d0)"},{"code":"ln_AO","name":"\u10da\u10d8\u10dc\u10d2\u10d0\u10da\u10d0 (\u10d0\u10dc\u10d2\u10dd\u10da\u10d0)"},{"code":"ln_CG","name":"\u10da\u10d8\u10dc\u10d2\u10d0\u10da\u10d0 (\u10d9\u10dd\u10dc\u10d2\u10dd - \u10d1\u10e0\u10d0\u10d6\u10d0\u10d5\u10d8\u10da\u10d8)"},{"code":"ln_CD","name":"\u10da\u10d8\u10dc\u10d2\u10d0\u10da\u10d0 (\u10d9\u10dd\u10dc\u10d2\u10dd - \u10d9\u10d8\u10dc\u10e8\u10d0\u10e1\u10d0)"},{"code":"ln_CF","name":"\u10da\u10d8\u10dc\u10d2\u10d0\u10da\u10d0 (\u10ea\u10d4\u10dc\u10e2\u10e0\u10d0\u10da\u10e3\u10e0\u10d8 \u10d0\u10e4\u10e0\u10d8\u10d9\u10d8\u10e1 \u10e0\u10d4\u10e1\u10de\u10e3\u10d1\u10da\u10d8\u10d9\u10d0)"},{"code":"lt_LT","name":"\u10da\u10d8\u10e2\u10d5\u10e3\u10e0\u10d8 (\u10da\u10d8\u10e2\u10d5\u10d0)"},{"code":"lu_CD","name":"\u10da\u10e3\u10d1\u10d0-\u10d9\u10d0\u10e2\u10d0\u10dc\u10d2\u10d0 (\u10d9\u10dd\u10dc\u10d2\u10dd - \u10d9\u10d8\u10dc\u10e8\u10d0\u10e1\u10d0)"},{"code":"lb_LU","name":"\u10da\u10e3\u10e5\u10e1\u10d4\u10db\u10d1\u10e3\u10e0\u10d2\u10e3\u10da\u10d8 (\u10da\u10e3\u10e5\u10e1\u10d4\u10db\u10d1\u10e3\u10e0\u10d2\u10d8)"},{"code":"mk_MK","name":"\u10db\u10d0\u10d9\u10d4\u10d3\u10dd\u10dc\u10e3\u10e0\u10d8 (\u10db\u10d0\u10d9\u10d4\u10d3\u10dd\u10dc\u10d8\u10d0)"},{"code":"mg_MG","name":"\u10db\u10d0\u10da\u10d0\u10d2\u10d0\u10e1\u10d8\u10e3\u10e0\u10d8 (\u10db\u10d0\u10d3\u10d0\u10d2\u10d0\u10e1\u10d9\u10d0\u10e0\u10d8)"},{"code":"ml_IN","name":"\u10db\u10d0\u10da\u10d0\u10d8\u10d0\u10da\u10d0\u10db\u10e3\u10e0\u10d8 (\u10d8\u10dc\u10d3\u10dd\u10d4\u10d7\u10d8)"},{"code":"ms_BN","name":"\u10db\u10d0\u10da\u10d0\u10d8\u10e3\u10e0\u10d8 (\u10d1\u10e0\u10e3\u10dc\u10d4\u10d8)"},{"code":"ms_MY","name":"\u10db\u10d0\u10da\u10d0\u10d8\u10e3\u10e0\u10d8 (\u10db\u10d0\u10da\u10d0\u10d8\u10d6\u10d8\u10d0)"},{"code":"ms_SG","name":"\u10db\u10d0\u10da\u10d0\u10d8\u10e3\u10e0\u10d8 (\u10e1\u10d8\u10dc\u10d2\u10d0\u10de\u10e3\u10e0\u10d8)"},{"code":"mt_MT","name":"\u10db\u10d0\u10da\u10e2\u10e3\u10e0\u10d8 (\u10db\u10d0\u10da\u10e2\u10d0)"},{"code":"mr_IN","name":"\u10db\u10d0\u10e0\u10d0\u10d7\u10f0\u10d8 (\u10d8\u10dc\u10d3\u10dd\u10d4\u10d7\u10d8)"},{"code":"gv_IM","name":"\u10db\u10d4\u10dc\u10e3\u10e0\u10d8 (\u10db\u10d4\u10dc\u10d8\u10e1 \u10d9\u10e3\u10dc\u10eb\u10e3\u10da\u10d8)"},{"code":"mn_MN","name":"\u10db\u10dd\u10dc\u10e6\u10dd\u10da\u10e3\u10e0\u10d8 (\u10db\u10dd\u10dc\u10e6\u10dd\u10da\u10d4\u10d7\u10d8)"},{"code":"ne_IN","name":"\u10dc\u10d4\u10de\u10d0\u10da\u10e3\u10e0\u10d8 (\u10d8\u10dc\u10d3\u10dd\u10d4\u10d7\u10d8)"},{"code":"ne_NP","name":"\u10dc\u10d4\u10de\u10d0\u10da\u10e3\u10e0\u10d8 (\u10dc\u10d4\u10de\u10d0\u10da\u10d8)"},{"code":"nl_AW","name":"\u10dc\u10d8\u10d3\u10d4\u10e0\u10da\u10d0\u10dc\u10d3\u10e3\u10e0\u10d8 (\u10d0\u10e0\u10e3\u10d1\u10d0)"},{"code":"nl_BE","name":"\u10dc\u10d8\u10d3\u10d4\u10e0\u10da\u10d0\u10dc\u10d3\u10e3\u10e0\u10d8 (\u10d1\u10d4\u10da\u10d2\u10d8\u10d0)"},{"code":"nl_BQ","name":"\u10dc\u10d8\u10d3\u10d4\u10e0\u10da\u10d0\u10dc\u10d3\u10e3\u10e0\u10d8 (\u10d9\u10d0\u10e0\u10d8\u10d1\u10d8\u10e1 \u10dc\u10d8\u10d3\u10d4\u10e0\u10da\u10d0\u10dc\u10d3\u10d4\u10d1\u10d8)"},{"code":"nl_CW","name":"\u10dc\u10d8\u10d3\u10d4\u10e0\u10da\u10d0\u10dc\u10d3\u10e3\u10e0\u10d8 (\u10d9\u10d8\u10e3\u10e0\u10d0\u10e1\u10d0\u10dd)"},{"code":"nl_NL","name":"\u10dc\u10d8\u10d3\u10d4\u10e0\u10da\u10d0\u10dc\u10d3\u10e3\u10e0\u10d8 (\u10dc\u10d8\u10d3\u10d4\u10e0\u10da\u10d0\u10dc\u10d3\u10d4\u10d1\u10d8)"},{"code":"nl_SX","name":"\u10dc\u10d8\u10d3\u10d4\u10e0\u10da\u10d0\u10dc\u10d3\u10e3\u10e0\u10d8 (\u10e1\u10d8\u10dc\u10e2-\u10db\u10d0\u10e0\u10e2\u10d4\u10dc\u10d8)"},{"code":"nl_SR","name":"\u10dc\u10d8\u10d3\u10d4\u10e0\u10da\u10d0\u10dc\u10d3\u10e3\u10e0\u10d8 (\u10e1\u10e3\u10e0\u10d8\u10dc\u10d0\u10db\u10d8)"},{"code":"no_NO","name":"\u10dc\u10dd\u10e0\u10d5\u10d4\u10d2\u10d8\u10e3\u10da\u10d8 (\u10dc\u10dd\u10e0\u10d5\u10d4\u10d2\u10d8\u10d0)"},{"code":"nb_NO","name":"\u10dc\u10dd\u10e0\u10d5\u10d4\u10d2\u10d8\u10e3\u10da\u10d8 \u10d1\u10e3\u10d9\u10db\u10dd\u10da\u10d8 (\u10dc\u10dd\u10e0\u10d5\u10d4\u10d2\u10d8\u10d0)"},{"code":"nb_SJ","name":"\u10dc\u10dd\u10e0\u10d5\u10d4\u10d2\u10d8\u10e3\u10da\u10d8 \u10d1\u10e3\u10d9\u10db\u10dd\u10da\u10d8 (\u10e8\u10de\u10d8\u10ea\u10d1\u10d4\u10e0\u10d2\u10d4\u10dc\u10d8 \u10d3\u10d0 \u10d8\u10d0\u10dc-\u10db\u10d0\u10d8\u10d4\u10dc\u10d8)"},{"code":"nn_NO","name":"\u10dc\u10dd\u10e0\u10d5\u10d4\u10d2\u10d8\u10e3\u10da\u10d8 \u10dc\u10d8\u10e3\u10dc\u10dd\u10e0\u10e1\u10d9\u10d8 (\u10dc\u10dd\u10e0\u10d5\u10d4\u10d2\u10d8\u10d0)"},{"code":"or_IN","name":"\u10dd\u10e0\u10d8\u10d0 (\u10d8\u10dc\u10d3\u10dd\u10d4\u10d7\u10d8)"},{"code":"om_ET","name":"\u10dd\u10e0\u10dd\u10db\u10dd (\u10d4\u10d7\u10d8\u10dd\u10de\u10d8\u10d0)"},{"code":"om_KE","name":"\u10dd\u10e0\u10dd\u10db\u10dd (\u10d9\u10d4\u10dc\u10d8\u10d0)"},{"code":"os_RU","name":"\u10dd\u10e1\u10e3\u10e0\u10d8 (\u10e0\u10e3\u10e1\u10d4\u10d7\u10d8)"},{"code":"os_GE","name":"\u10dd\u10e1\u10e3\u10e0\u10d8 (\u10e1\u10d0\u10e5\u10d0\u10e0\u10d7\u10d5\u10d4\u10da\u10dd)"},{"code":"pa_IN","name":"\u10de\u10d4\u10dc\u10ef\u10d0\u10d1\u10e3\u10e0\u10d8 (\u10d8\u10dc\u10d3\u10dd\u10d4\u10d7\u10d8)"},{"code":"pa_PK","name":"\u10de\u10d4\u10dc\u10ef\u10d0\u10d1\u10e3\u10e0\u10d8 (\u10de\u10d0\u10d9\u10d8\u10e1\u10e2\u10d0\u10dc\u10d8)"},{"code":"pl_PL","name":"\u10de\u10dd\u10da\u10dd\u10dc\u10e3\u10e0\u10d8 (\u10de\u10dd\u10da\u10dd\u10dc\u10d4\u10d7\u10d8)"},{"code":"pt_AO","name":"\u10de\u10dd\u10e0\u10e2\u10e3\u10d2\u10d0\u10da\u10d8\u10e3\u10e0\u10d8 (\u10d0\u10dc\u10d2\u10dd\u10da\u10d0)"},{"code":"pt_BR","name":"\u10de\u10dd\u10e0\u10e2\u10e3\u10d2\u10d0\u10da\u10d8\u10e3\u10e0\u10d8 (\u10d1\u10e0\u10d0\u10d6\u10d8\u10da\u10d8\u10d0)"},{"code":"pt_GW","name":"\u10de\u10dd\u10e0\u10e2\u10e3\u10d2\u10d0\u10da\u10d8\u10e3\u10e0\u10d8 (\u10d2\u10d5\u10d8\u10dc\u10d4\u10d0-\u10d1\u10d8\u10e1\u10d0\u10e3)"},{"code":"pt_CV","name":"\u10de\u10dd\u10e0\u10e2\u10e3\u10d2\u10d0\u10da\u10d8\u10e3\u10e0\u10d8 (\u10d9\u10d0\u10d1\u10dd-\u10d5\u10d4\u10e0\u10d3\u10d4)"},{"code":"pt_MO","name":"\u10de\u10dd\u10e0\u10e2\u10e3\u10d2\u10d0\u10da\u10d8\u10e3\u10e0\u10d8 (\u10db\u10d0\u10d9\u10d0\u10dd\u10e1 \u10e1\u10de\u10d4\u10ea\u10d8\u10d0\u10da\u10e3\u10e0\u10d8 \u10d0\u10d3\u10db\u10d8\u10dc\u10d8\u10e1\u10e2\u10e0\u10d0\u10ea\u10d8\u10e3\u10da\u10d8 \u10e0\u10d4\u10d2\u10d8\u10dd\u10dc\u10d8 \u10e9\u10d8\u10dc\u10d4\u10d7\u10d8)"},{"code":"pt_MZ","name":"\u10de\u10dd\u10e0\u10e2\u10e3\u10d2\u10d0\u10da\u10d8\u10e3\u10e0\u10d8 (\u10db\u10dd\u10d6\u10d0\u10db\u10d1\u10d8\u10d9\u10d8)"},{"code":"pt_PT","name":"\u10de\u10dd\u10e0\u10e2\u10e3\u10d2\u10d0\u10da\u10d8\u10e3\u10e0\u10d8 (\u10de\u10dd\u10e0\u10e2\u10e3\u10d2\u10d0\u10da\u10d8\u10d0)"},{"code":"pt_ST","name":"\u10de\u10dd\u10e0\u10e2\u10e3\u10d2\u10d0\u10da\u10d8\u10e3\u10e0\u10d8 (\u10e1\u10d0\u10dc-\u10e2\u10dd\u10db\u10d4 \u10d3\u10d0 \u10de\u10e0\u10d8\u10dc\u10e1\u10d8\u10de\u10d8)"},{"code":"pt_TL","name":"\u10de\u10dd\u10e0\u10e2\u10e3\u10d2\u10d0\u10da\u10d8\u10e3\u10e0\u10d8 (\u10e2\u10d8\u10db\u10dd\u10e0-\u10da\u10d4\u10e8\u10e2\u10d8)"},{"code":"ps_AF","name":"\u10de\u10e3\u10e8\u10e2\u10e3 (\u10d0\u10d5\u10e6\u10d0\u10dc\u10d4\u10d7\u10d8)"},{"code":"rm_CH","name":"\u10e0\u10d4\u10e2\u10dd\u10e0\u10dd\u10db\u10d0\u10dc\u10e3\u10da\u10d8 (\u10e8\u10d5\u10d4\u10d8\u10ea\u10d0\u10e0\u10d8\u10d0)"},{"code":"ro_MD","name":"\u10e0\u10e3\u10db\u10d8\u10dc\u10e3\u10da\u10d8 (\u10db\u10dd\u10da\u10d3\u10dd\u10d5\u10d0)"},{"code":"ro_RO","name":"\u10e0\u10e3\u10db\u10d8\u10dc\u10e3\u10da\u10d8 (\u10e0\u10e3\u10db\u10d8\u10dc\u10d4\u10d7\u10d8)"},{"code":"rn_BI","name":"\u10e0\u10e3\u10dc\u10d3\u10d8 (\u10d1\u10e3\u10e0\u10e3\u10dc\u10d3\u10d8)"},{"code":"ru_BY","name":"\u10e0\u10e3\u10e1\u10e3\u10da\u10d8 (\u10d1\u10d4\u10da\u10dd\u10e0\u10e3\u10e1\u10d8\u10d0)"},{"code":"ru_MD","name":"\u10e0\u10e3\u10e1\u10e3\u10da\u10d8 (\u10db\u10dd\u10da\u10d3\u10dd\u10d5\u10d0)"},{"code":"ru_RU","name":"\u10e0\u10e3\u10e1\u10e3\u10da\u10d8 (\u10e0\u10e3\u10e1\u10d4\u10d7\u10d8)"},{"code":"ru_UA","name":"\u10e0\u10e3\u10e1\u10e3\u10da\u10d8 (\u10e3\u10d9\u10e0\u10d0\u10d8\u10dc\u10d0)"},{"code":"ru_KZ","name":"\u10e0\u10e3\u10e1\u10e3\u10da\u10d8 (\u10e7\u10d0\u10d6\u10d0\u10ee\u10d4\u10d7\u10d8)"},{"code":"ru_KG","name":"\u10e0\u10e3\u10e1\u10e3\u10da\u10d8 (\u10e7\u10d8\u10e0\u10d2\u10d8\u10d6\u10d4\u10d7\u10d8)"},{"code":"sg_CF","name":"\u10e1\u10d0\u10dc\u10d2\u10dd (\u10ea\u10d4\u10dc\u10e2\u10e0\u10d0\u10da\u10e3\u10e0\u10d8 \u10d0\u10e4\u10e0\u10d8\u10d9\u10d8\u10e1 \u10e0\u10d4\u10e1\u10de\u10e3\u10d1\u10da\u10d8\u10d9\u10d0)"},{"code":"sh_BA","name":"\u10e1\u10d4\u10e0\u10d1\u10e3\u10da-\u10ee\u10dd\u10e0\u10d5\u10d0\u10e2\u10e3\u10da\u10d8 (\u10d1\u10dd\u10e1\u10dc\u10d8\u10d0 \u10d3\u10d0 \u10f0\u10d4\u10e0\u10ea\u10d4\u10d2\u10dd\u10d5\u10d8\u10dc\u10d0)"},{"code":"sr_BA","name":"\u10e1\u10d4\u10e0\u10d1\u10e3\u10da\u10d8 (\u10d1\u10dd\u10e1\u10dc\u10d8\u10d0 \u10d3\u10d0 \u10f0\u10d4\u10e0\u10ea\u10d4\u10d2\u10dd\u10d5\u10d8\u10dc\u10d0)"},{"code":"sr_XK","name":"\u10e1\u10d4\u10e0\u10d1\u10e3\u10da\u10d8 (\u10d9\u10dd\u10e1\u10dd\u10d5\u10dd)"},{"code":"sr_ME","name":"\u10e1\u10d4\u10e0\u10d1\u10e3\u10da\u10d8 (\u10db\u10dd\u10dc\u10e2\u10d4\u10dc\u10d4\u10d2\u10e0\u10dd)"},{"code":"sr_RS","name":"\u10e1\u10d4\u10e0\u10d1\u10e3\u10da\u10d8 (\u10e1\u10d4\u10e0\u10d1\u10d4\u10d7\u10d8)"},{"code":"si_LK","name":"\u10e1\u10d8\u10dc\u10f0\u10d0\u10da\u10e3\u10e0\u10d8 (\u10e8\u10e0\u10d8-\u10da\u10d0\u10dc\u10d9\u10d0)"},{"code":"ii_CN","name":"\u10e1\u10d8\u10e9\u10e3\u10d0\u10dc\u10d8\u10e1 \u10d8 (\u10e9\u10d8\u10dc\u10d4\u10d7\u10d8)"},{"code":"sk_SK","name":"\u10e1\u10da\u10dd\u10d5\u10d0\u10d9\u10e3\u10e0\u10d8 (\u10e1\u10da\u10dd\u10d5\u10d0\u10d9\u10d4\u10d7\u10d8)"},{"code":"sl_SI","name":"\u10e1\u10da\u10dd\u10d5\u10d4\u10dc\u10e3\u10e0\u10d8 (\u10e1\u10da\u10dd\u10d5\u10d4\u10dc\u10d8\u10d0)"},{"code":"so_ET","name":"\u10e1\u10dd\u10db\u10d0\u10da\u10d8\u10e3\u10e0\u10d8 (\u10d4\u10d7\u10d8\u10dd\u10de\u10d8\u10d0)"},{"code":"so_KE","name":"\u10e1\u10dd\u10db\u10d0\u10da\u10d8\u10e3\u10e0\u10d8 (\u10d9\u10d4\u10dc\u10d8\u10d0)"},{"code":"so_SO","name":"\u10e1\u10dd\u10db\u10d0\u10da\u10d8\u10e3\u10e0\u10d8 (\u10e1\u10dd\u10db\u10d0\u10da\u10d8)"},{"code":"so_DJ","name":"\u10e1\u10dd\u10db\u10d0\u10da\u10d8\u10e3\u10e0\u10d8 (\u10ef\u10d8\u10d1\u10e3\u10e2\u10d8)"},{"code":"hy_AM","name":"\u10e1\u10dd\u10db\u10ee\u10e3\u10e0\u10d8 (\u10e1\u10dd\u10db\u10ee\u10d4\u10d7\u10d8)"},{"code":"fa_AF","name":"\u10e1\u10de\u10d0\u10e0\u10e1\u10e3\u10da\u10d8 (\u10d0\u10d5\u10e6\u10d0\u10dc\u10d4\u10d7\u10d8)"},{"code":"fa_IR","name":"\u10e1\u10de\u10d0\u10e0\u10e1\u10e3\u10da\u10d8 (\u10d8\u10e0\u10d0\u10dc\u10d8)"},{"code":"sw_KE","name":"\u10e1\u10e3\u10d0\u10f0\u10d8\u10da\u10d8 (\u10d9\u10d4\u10dc\u10d8\u10d0)"},{"code":"sw_TZ","name":"\u10e1\u10e3\u10d0\u10f0\u10d8\u10da\u10d8 (\u10e2\u10d0\u10dc\u10d6\u10d0\u10dc\u10d8\u10d0)"},{"code":"sw_UG","name":"\u10e1\u10e3\u10d0\u10f0\u10d8\u10da\u10d8 (\u10e3\u10d2\u10d0\u10dc\u10d3\u10d0)"},{"code":"th_TH","name":"\u10e2\u10d0\u10d8 (\u10e2\u10d0\u10d8\u10da\u10d0\u10dc\u10d3\u10d8)"},{"code":"ta_IN","name":"\u10e2\u10d0\u10db\u10d8\u10da\u10e3\u10e0\u10d8 (\u10d8\u10dc\u10d3\u10dd\u10d4\u10d7\u10d8)"},{"code":"ta_MY","name":"\u10e2\u10d0\u10db\u10d8\u10da\u10e3\u10e0\u10d8 (\u10db\u10d0\u10da\u10d0\u10d8\u10d6\u10d8\u10d0)"},{"code":"ta_SG","name":"\u10e2\u10d0\u10db\u10d8\u10da\u10e3\u10e0\u10d8 (\u10e1\u10d8\u10dc\u10d2\u10d0\u10de\u10e3\u10e0\u10d8)"},{"code":"ta_LK","name":"\u10e2\u10d0\u10db\u10d8\u10da\u10e3\u10e0\u10d8 (\u10e8\u10e0\u10d8-\u10da\u10d0\u10dc\u10d9\u10d0)"},{"code":"te_IN","name":"\u10e2\u10d4\u10da\u10e3\u10d2\u10e3 (\u10d8\u10dc\u10d3\u10dd\u10d4\u10d7\u10d8)"},{"code":"bo_IN","name":"\u10e2\u10d8\u10d1\u10d4\u10e2\u10e3\u10e0\u10d8 (\u10d8\u10dc\u10d3\u10dd\u10d4\u10d7\u10d8)"},{"code":"bo_CN","name":"\u10e2\u10d8\u10d1\u10d4\u10e2\u10e3\u10e0\u10d8 (\u10e9\u10d8\u10dc\u10d4\u10d7\u10d8)"},{"code":"to_TO","name":"\u10e2\u10dd\u10dc\u10d2\u10d0\u10dc\u10e3\u10e0\u10d8 (\u10e2\u10dd\u10dc\u10d2\u10d0)"},{"code":"cy_GB","name":"\u10e3\u10d4\u10da\u10e1\u10e3\u10e0\u10d8 (\u10d3\u10d8\u10d3\u10d8 \u10d1\u10e0\u10d8\u10e2\u10d0\u10dc\u10d4\u10d7\u10d8)"},{"code":"uz_AF","name":"\u10e3\u10d6\u10d1\u10d4\u10d9\u10e3\u10e0\u10d8 (\u10d0\u10d5\u10e6\u10d0\u10dc\u10d4\u10d7\u10d8)"},{"code":"uz_UZ","name":"\u10e3\u10d6\u10d1\u10d4\u10d9\u10e3\u10e0\u10d8 (\u10e3\u10d6\u10d1\u10d4\u10d9\u10d4\u10d7\u10d8)"},{"code":"ug_CN","name":"\u10e3\u10d8\u10e6\u10e3\u10e0\u10e3\u10da\u10d8 (\u10e9\u10d8\u10dc\u10d4\u10d7\u10d8)"},{"code":"uk_UA","name":"\u10e3\u10d9\u10e0\u10d0\u10d8\u10dc\u10e3\u10da\u10d8 (\u10e3\u10d9\u10e0\u10d0\u10d8\u10dc\u10d0)"},{"code":"hu_HU","name":"\u10e3\u10dc\u10d2\u10e0\u10e3\u10da\u10d8 (\u10e3\u10dc\u10d2\u10e0\u10d4\u10d7\u10d8)"},{"code":"ur_IN","name":"\u10e3\u10e0\u10d3\u10e3 (\u10d8\u10dc\u10d3\u10dd\u10d4\u10d7\u10d8)"},{"code":"ur_PK","name":"\u10e3\u10e0\u10d3\u10e3 (\u10de\u10d0\u10d9\u10d8\u10e1\u10e2\u10d0\u10dc\u10d8)"},{"code":"fo_FO","name":"\u10e4\u10d0\u10e0\u10d4\u10e0\u10e3\u10da\u10d8 (\u10e4\u10d0\u10e0\u10d4\u10e0\u10d8\u10e1 \u10d9\u10e3\u10dc\u10eb\u10e3\u10da\u10d4\u10d1\u10d8)"},{"code":"fi_FI","name":"\u10e4\u10d8\u10dc\u10e3\u10e0\u10d8 (\u10e4\u10d8\u10dc\u10d4\u10d7\u10d8)"},{"code":"fr_DZ","name":"\u10e4\u10e0\u10d0\u10dc\u10d2\u10e3\u10da\u10d8 (\u10d0\u10da\u10df\u10d8\u10e0\u10d8)"},{"code":"fr_NC","name":"\u10e4\u10e0\u10d0\u10dc\u10d2\u10e3\u10da\u10d8 (\u10d0\u10ee\u10d0\u10da\u10d8 \u10d9\u10d0\u10da\u10d4\u10d3\u10dd\u10dc\u10d8\u10d0)"},{"code":"fr_BE","name":"\u10e4\u10e0\u10d0\u10dc\u10d2\u10e3\u10da\u10d8 (\u10d1\u10d4\u10da\u10d2\u10d8\u10d0)"},{"code":"fr_BJ","name":"\u10e4\u10e0\u10d0\u10dc\u10d2\u10e3\u10da\u10d8 (\u10d1\u10d4\u10dc\u10d8\u10dc\u10d8)"},{"code":"fr_BF","name":"\u10e4\u10e0\u10d0\u10dc\u10d2\u10e3\u10da\u10d8 (\u10d1\u10e3\u10e0\u10d9\u10d8\u10dc\u10d0-\u10e4\u10d0\u10e1\u10dd)"},{"code":"fr_BI","name":"\u10e4\u10e0\u10d0\u10dc\u10d2\u10e3\u10da\u10d8 (\u10d1\u10e3\u10e0\u10e3\u10dc\u10d3\u10d8)"},{"code":"fr_GA","name":"\u10e4\u10e0\u10d0\u10dc\u10d2\u10e3\u10da\u10d8 (\u10d2\u10d0\u10d1\u10dd\u10dc\u10d8)"},{"code":"fr_GP","name":"\u10e4\u10e0\u10d0\u10dc\u10d2\u10e3\u10da\u10d8 (\u10d2\u10d5\u10d0\u10d3\u10d4\u10da\u10e3\u10de\u10d4)"},{"code":"fr_GN","name":"\u10e4\u10e0\u10d0\u10dc\u10d2\u10e3\u10da\u10d8 (\u10d2\u10d5\u10d8\u10dc\u10d4\u10d0)"},{"code":"fr_GQ","name":"\u10e4\u10e0\u10d0\u10dc\u10d2\u10e3\u10da\u10d8 (\u10d4\u10d9\u10d5\u10d0\u10e2\u10dd\u10e0\u10e3\u10da\u10d8 \u10d2\u10d5\u10d8\u10dc\u10d4\u10d0)"},{"code":"fr_VU","name":"\u10e4\u10e0\u10d0\u10dc\u10d2\u10e3\u10da\u10d8 (\u10d5\u10d0\u10dc\u10e3\u10d0\u10e2\u10e3)"},{"code":"fr_CM","name":"\u10e4\u10e0\u10d0\u10dc\u10d2\u10e3\u10da\u10d8 (\u10d9\u10d0\u10db\u10d4\u10e0\u10e3\u10dc\u10d8)"},{"code":"fr_CA","name":"\u10e4\u10e0\u10d0\u10dc\u10d2\u10e3\u10da\u10d8 (\u10d9\u10d0\u10dc\u10d0\u10d3\u10d0)"},{"code":"fr_KM","name":"\u10e4\u10e0\u10d0\u10dc\u10d2\u10e3\u10da\u10d8 (\u10d9\u10dd\u10db\u10dd\u10e0\u10d8\u10e1 \u10d9\u10e3\u10dc\u10eb\u10e3\u10da\u10d4\u10d1\u10d8)"},{"code":"fr_CG","name":"\u10e4\u10e0\u10d0\u10dc\u10d2\u10e3\u10da\u10d8 (\u10d9\u10dd\u10dc\u10d2\u10dd - \u10d1\u10e0\u10d0\u10d6\u10d0\u10d5\u10d8\u10da\u10d8)"},{"code":"fr_CD","name":"\u10e4\u10e0\u10d0\u10dc\u10d2\u10e3\u10da\u10d8 (\u10d9\u10dd\u10dc\u10d2\u10dd - \u10d9\u10d8\u10dc\u10e8\u10d0\u10e1\u10d0)"},{"code":"fr_CI","name":"\u10e4\u10e0\u10d0\u10dc\u10d2\u10e3\u10da\u10d8 (\u10d9\u10dd\u10e2-\u10d3\u10d8\u10d5\u10e3\u10d0\u10e0\u10d8)"},{"code":"fr_LU","name":"\u10e4\u10e0\u10d0\u10dc\u10d2\u10e3\u10da\u10d8 (\u10da\u10e3\u10e5\u10e1\u10d4\u10db\u10d1\u10e3\u10e0\u10d2\u10d8)"},{"code":"fr_MG","name":"\u10e4\u10e0\u10d0\u10dc\u10d2\u10e3\u10da\u10d8 (\u10db\u10d0\u10d3\u10d0\u10d2\u10d0\u10e1\u10d9\u10d0\u10e0\u10d8)"},{"code":"fr_MU","name":"\u10e4\u10e0\u10d0\u10dc\u10d2\u10e3\u10da\u10d8 (\u10db\u10d0\u10d5\u10e0\u10d8\u10d9\u10d8)"},{"code":"fr_MR","name":"\u10e4\u10e0\u10d0\u10dc\u10d2\u10e3\u10da\u10d8 (\u10db\u10d0\u10d5\u10e0\u10d8\u10e2\u10d0\u10dc\u10d8\u10d0)"},{"code":"fr_YT","name":"\u10e4\u10e0\u10d0\u10dc\u10d2\u10e3\u10da\u10d8 (\u10db\u10d0\u10d8\u10dd\u10e2\u10d0)"},{"code":"fr_ML","name":"\u10e4\u10e0\u10d0\u10dc\u10d2\u10e3\u10da\u10d8 (\u10db\u10d0\u10da\u10d8)"},{"code":"fr_MA","name":"\u10e4\u10e0\u10d0\u10dc\u10d2\u10e3\u10da\u10d8 (\u10db\u10d0\u10e0\u10dd\u10d9\u10dd)"},{"code":"fr_MQ","name":"\u10e4\u10e0\u10d0\u10dc\u10d2\u10e3\u10da\u10d8 (\u10db\u10d0\u10e0\u10e2\u10d8\u10dc\u10d8\u10d9\u10d0)"},{"code":"fr_MC","name":"\u10e4\u10e0\u10d0\u10dc\u10d2\u10e3\u10da\u10d8 (\u10db\u10dd\u10dc\u10d0\u10d9\u10dd)"},{"code":"fr_NE","name":"\u10e4\u10e0\u10d0\u10dc\u10d2\u10e3\u10da\u10d8 (\u10dc\u10d8\u10d2\u10d4\u10e0\u10d8)"},{"code":"fr_RE","name":"\u10e4\u10e0\u10d0\u10dc\u10d2\u10e3\u10da\u10d8 (\u10e0\u10d4\u10e3\u10dc\u10d8\u10dd\u10dc\u10d8)"},{"code":"fr_RW","name":"\u10e4\u10e0\u10d0\u10dc\u10d2\u10e3\u10da\u10d8 (\u10e0\u10e3\u10d0\u10dc\u10d3\u10d0)"},{"code":"fr_FR","name":"\u10e4\u10e0\u10d0\u10dc\u10d2\u10e3\u10da\u10d8 (\u10e1\u10d0\u10e4\u10e0\u10d0\u10dc\u10d2\u10d4\u10d7\u10d8)"},{"code":"fr_SC","name":"\u10e4\u10e0\u10d0\u10dc\u10d2\u10e3\u10da\u10d8 (\u10e1\u10d4\u10d8\u10e8\u10d4\u10da\u10d8\u10e1 \u10d9\u10e3\u10dc\u10eb\u10e3\u10da\u10d4\u10d1\u10d8)"},{"code":"fr_BL","name":"\u10e4\u10e0\u10d0\u10dc\u10d2\u10e3\u10da\u10d8 (\u10e1\u10d4\u10dc-\u10d1\u10d0\u10e0\u10d7\u10da\u10d4\u10db\u10d8)"},{"code":"fr_MF","name":"\u10e4\u10e0\u10d0\u10dc\u10d2\u10e3\u10da\u10d8 (\u10e1\u10d4\u10dc-\u10db\u10d0\u10e0\u10e2\u10d4\u10dc\u10d8)"},{"code":"fr_PM","name":"\u10e4\u10e0\u10d0\u10dc\u10d2\u10e3\u10da\u10d8 (\u10e1\u10d4\u10dc-\u10de\u10d8\u10d4\u10e0\u10d8 \u10d3\u10d0 \u10db\u10d8\u10d9\u10d4\u10da\u10dd\u10dc\u10d8)"},{"code":"fr_SN","name":"\u10e4\u10e0\u10d0\u10dc\u10d2\u10e3\u10da\u10d8 (\u10e1\u10d4\u10dc\u10d4\u10d2\u10d0\u10da\u10d8)"},{"code":"fr_SY","name":"\u10e4\u10e0\u10d0\u10dc\u10d2\u10e3\u10da\u10d8 (\u10e1\u10d8\u10e0\u10d8\u10d0)"},{"code":"fr_TG","name":"\u10e4\u10e0\u10d0\u10dc\u10d2\u10e3\u10da\u10d8 (\u10e2\u10dd\u10d2\u10dd)"},{"code":"fr_TN","name":"\u10e4\u10e0\u10d0\u10dc\u10d2\u10e3\u10da\u10d8 (\u10e2\u10e3\u10dc\u10d8\u10e1\u10d8)"},{"code":"fr_WF","name":"\u10e4\u10e0\u10d0\u10dc\u10d2\u10e3\u10da\u10d8 (\u10e3\u10dd\u10da\u10d8\u10e1\u10d8 \u10d3\u10d0 \u10e4\u10e3\u10e2\u10e3\u10dc\u10d0)"},{"code":"fr_GF","name":"\u10e4\u10e0\u10d0\u10dc\u10d2\u10e3\u10da\u10d8 (\u10e4\u10e0\u10d0\u10dc\u10d2\u10e3\u10da\u10d8 \u10d2\u10d5\u10d8\u10d0\u10dc\u10d0)"},{"code":"fr_PF","name":"\u10e4\u10e0\u10d0\u10dc\u10d2\u10e3\u10da\u10d8 (\u10e4\u10e0\u10d0\u10dc\u10d2\u10e3\u10da\u10d8 \u10de\u10dd\u10da\u10d8\u10dc\u10d4\u10d6\u10d8\u10d0)"},{"code":"fr_CH","name":"\u10e4\u10e0\u10d0\u10dc\u10d2\u10e3\u10da\u10d8 (\u10e8\u10d5\u10d4\u10d8\u10ea\u10d0\u10e0\u10d8\u10d0)"},{"code":"fr_TD","name":"\u10e4\u10e0\u10d0\u10dc\u10d2\u10e3\u10da\u10d8 (\u10e9\u10d0\u10d3\u10d8)"},{"code":"fr_CF","name":"\u10e4\u10e0\u10d0\u10dc\u10d2\u10e3\u10da\u10d8 (\u10ea\u10d4\u10dc\u10e2\u10e0\u10d0\u10da\u10e3\u10e0\u10d8 \u10d0\u10e4\u10e0\u10d8\u10d9\u10d8\u10e1 \u10e0\u10d4\u10e1\u10de\u10e3\u10d1\u10da\u10d8\u10d9\u10d0)"},{"code":"fr_DJ","name":"\u10e4\u10e0\u10d0\u10dc\u10d2\u10e3\u10da\u10d8 (\u10ef\u10d8\u10d1\u10e3\u10e2\u10d8)"},{"code":"fr_HT","name":"\u10e4\u10e0\u10d0\u10dc\u10d2\u10e3\u10da\u10d8 (\u10f0\u10d0\u10d8\u10e2\u10d8)"},{"code":"ka_GE","name":"\u10e5\u10d0\u10e0\u10d7\u10e3\u10da\u10d8 (\u10e1\u10d0\u10e5\u10d0\u10e0\u10d7\u10d5\u10d4\u10da\u10dd)"},{"code":"ks_IN","name":"\u10e5\u10d0\u10e8\u10db\u10d8\u10e0\u10e3\u10da\u10d8 (\u10d8\u10dc\u10d3\u10dd\u10d4\u10d7\u10d8)"},{"code":"km_KH","name":"\u10e5\u10db\u10d4\u10e0\u10e3\u10da\u10d8 (\u10d9\u10d0\u10db\u10d1\u10dd\u10ef\u10d0)"},{"code":"kk_KZ","name":"\u10e7\u10d0\u10d6\u10d0\u10ee\u10e3\u10e0\u10d8 (\u10e7\u10d0\u10d6\u10d0\u10ee\u10d4\u10d7\u10d8)"},{"code":"ky_KG","name":"\u10e7\u10d8\u10e0\u10d2\u10d8\u10d6\u10e3\u10da\u10d8 (\u10e7\u10d8\u10e0\u10d2\u10d8\u10d6\u10d4\u10d7\u10d8)"},{"code":"sv_AX","name":"\u10e8\u10d5\u10d4\u10d3\u10e3\u10e0\u10d8 (\u10d0\u10da\u10d0\u10dc\u10d3\u10d8\u10e1 \u10d9\u10e3\u10dc\u10eb\u10e3\u10da\u10d4\u10d1\u10d8)"},{"code":"sv_FI","name":"\u10e8\u10d5\u10d4\u10d3\u10e3\u10e0\u10d8 (\u10e4\u10d8\u10dc\u10d4\u10d7\u10d8)"},{"code":"sv_SE","name":"\u10e8\u10d5\u10d4\u10d3\u10e3\u10e0\u10d8 (\u10e8\u10d5\u10d4\u10d3\u10d4\u10d7\u10d8)"},{"code":"sn_ZW","name":"\u10e8\u10dd\u10dc\u10d0 (\u10d6\u10d8\u10db\u10d1\u10d0\u10d1\u10d5\u10d4)"},{"code":"gd_GB","name":"\u10e8\u10dd\u10e2\u10da\u10d0\u10dc\u10d3\u10d8\u10e3\u10e0\u10d8 \u10d2\u10d4\u10da\u10e3\u10e0\u10d8 (\u10d3\u10d8\u10d3\u10d8 \u10d1\u10e0\u10d8\u10e2\u10d0\u10dc\u10d4\u10d7\u10d8)"},{"code":"cs_CZ","name":"\u10e9\u10d4\u10ee\u10e3\u10e0\u10d8 (\u10e9\u10d4\u10ee\u10d4\u10d7\u10d8\u10e1 \u10e0\u10d4\u10e1\u10de\u10e3\u10d1\u10da\u10d8\u10d9\u10d0)"},{"code":"zh_MO","name":"\u10e9\u10d8\u10dc\u10e3\u10e0\u10d8 (\u10db\u10d0\u10d9\u10d0\u10dd\u10e1 \u10e1\u10de\u10d4\u10ea\u10d8\u10d0\u10da\u10e3\u10e0\u10d8 \u10d0\u10d3\u10db\u10d8\u10dc\u10d8\u10e1\u10e2\u10e0\u10d0\u10ea\u10d8\u10e3\u10da\u10d8 \u10e0\u10d4\u10d2\u10d8\u10dd\u10dc\u10d8 \u10e9\u10d8\u10dc\u10d4\u10d7\u10d8)"},{"code":"zh_SG","name":"\u10e9\u10d8\u10dc\u10e3\u10e0\u10d8 (\u10e1\u10d8\u10dc\u10d2\u10d0\u10de\u10e3\u10e0\u10d8)"},{"code":"zh_TW","name":"\u10e9\u10d8\u10dc\u10e3\u10e0\u10d8 (\u10e2\u10d0\u10d8\u10d5\u10d0\u10dc\u10d8)"},{"code":"zh_CN","name":"\u10e9\u10d8\u10dc\u10e3\u10e0\u10d8 (\u10e9\u10d8\u10dc\u10d4\u10d7\u10d8)"},{"code":"zh_HK","name":"\u10e9\u10d8\u10dc\u10e3\u10e0\u10d8 (\u10f0\u10dd\u10dc\u10d9\u10dd\u10dc\u10d2\u10d8\u10e1 \u10e1\u10de\u10d4\u10ea\u10d8\u10d0\u10da\u10e3\u10e0\u10d8 \u10d0\u10d3\u10db\u10d8\u10dc\u10d8\u10e1\u10e2\u10e0\u10d0\u10ea\u10d8\u10e3\u10da\u10d8 \u10e0\u10d4\u10d2\u10d8\u10dd\u10dc\u10d8 \u10e9\u10d8\u10dc\u10d4\u10d7\u10d8)"},{"code":"nd_ZW","name":"\u10e9\u10e0\u10d3\u10d8\u10da\u10dd\u10d4\u10d7 \u10dc\u10d3\u10d4\u10d1\u10d4\u10da\u10d4 (\u10d6\u10d8\u10db\u10d1\u10d0\u10d1\u10d5\u10d4)"},{"code":"se_NO","name":"\u10e9\u10e0\u10d3\u10d8\u10da\u10dd\u10d4\u10d7 \u10e1\u10d0\u10d0\u10db\u10e3\u10e0\u10d8 (\u10dc\u10dd\u10e0\u10d5\u10d4\u10d2\u10d8\u10d0)"},{"code":"se_FI","name":"\u10e9\u10e0\u10d3\u10d8\u10da\u10dd\u10d4\u10d7 \u10e1\u10d0\u10d0\u10db\u10e3\u10e0\u10d8 (\u10e4\u10d8\u10dc\u10d4\u10d7\u10d8)"},{"code":"se_SE","name":"\u10e9\u10e0\u10d3\u10d8\u10da\u10dd\u10d4\u10d7 \u10e1\u10d0\u10d0\u10db\u10e3\u10e0\u10d8 (\u10e8\u10d5\u10d4\u10d3\u10d4\u10d7\u10d8)"},{"code":"dz_BT","name":"\u10eb\u10dd\u10dc\u10d2\u10d9\u10ee\u10d0 (\u10d1\u10e3\u10e2\u10d0\u10dc\u10d8)"},{"code":"hr_BA","name":"\u10ee\u10dd\u10e0\u10d5\u10d0\u10e2\u10e3\u10da\u10d8 (\u10d1\u10dd\u10e1\u10dc\u10d8\u10d0 \u10d3\u10d0 \u10f0\u10d4\u10e0\u10ea\u10d4\u10d2\u10dd\u10d5\u10d8\u10dc\u10d0)"},{"code":"hr_HR","name":"\u10ee\u10dd\u10e0\u10d5\u10d0\u10e2\u10e3\u10da\u10d8 (\u10ee\u10dd\u10e0\u10d5\u10d0\u10e2\u10d8\u10d0)"},{"code":"ha_GH","name":"\u10f0\u10d0\u10e3\u10e1\u10d0 (\u10d2\u10d0\u10dc\u10d0)"},{"code":"ha_NE","name":"\u10f0\u10d0\u10e3\u10e1\u10d0 (\u10dc\u10d8\u10d2\u10d4\u10e0\u10d8)"},{"code":"ha_NG","name":"\u10f0\u10d0\u10e3\u10e1\u10d0 (\u10dc\u10d8\u10d2\u10d4\u10e0\u10d8\u10d0)"},{"code":"hi_IN","name":"\u10f0\u10d8\u10dc\u10d3\u10d8 (\u10d8\u10dc\u10d3\u10dd\u10d4\u10d7\u10d8)"}]