[{"code":"af_ZA","name":"afrikancha (Janubi-Afrika)"},{"code":"af_NA","name":"afrikancha (Namibiya)"},{"code":"ak_GH","name":"akancha (Gana)"},{"code":"sq_AL","name":"albancha (Albaniya)"},{"code":"sq_XK","name":"albancha (Kosovo)"},{"code":"sq_MK","name":"albancha (Makedoniya)"},{"code":"am_ET","name":"amxarcha (Efiopiya)"},{"code":"ar_BH","name":"arabcha (Bahrayn)"},{"code":"ar_AE","name":"arabcha (Birlashgan Arab Amirliklari)"},{"code":"ar_TD","name":"arabcha (Chad)"},{"code":"ar_DJ","name":"arabcha (Djibuti)"},{"code":"ar_ER","name":"arabcha (Eritreya)"},{"code":"ar_PS","name":"arabcha (Falastin hududi)"},{"code":"ar_EH","name":"arabcha (G\u02bbarbiy Sahroi Kabir)"},{"code":"ar_JO","name":"arabcha (Iordaniya)"},{"code":"ar_IQ","name":"arabcha (Iroq)"},{"code":"ar_IL","name":"arabcha (Isroil)"},{"code":"ar_SS","name":"arabcha (Janubiy Sudan)"},{"code":"ar_DZ","name":"arabcha (Jazoir)"},{"code":"ar_KM","name":"arabcha (Komor orollari)"},{"code":"ar_LB","name":"arabcha (Livan)"},{"code":"ar_LY","name":"arabcha (Liviya)"},{"code":"ar_MA","name":"arabcha (Marokash)"},{"code":"ar_MR","name":"arabcha (Mavritaniya)"},{"code":"ar_EG","name":"arabcha (Misr)"},{"code":"ar_OM","name":"arabcha (Omon)"},{"code":"ar_QA","name":"arabcha (Qatar)"},{"code":"ar_KW","name":"arabcha (Quveyt)"},{"code":"ar_SA","name":"arabcha (Saudiya Arabistoni)"},{"code":"ar_SO","name":"arabcha (Somali)"},{"code":"ar_SD","name":"arabcha (Sudan)"},{"code":"ar_SY","name":"arabcha (Suriya)"},{"code":"ar_TN","name":"arabcha (Tunis)"},{"code":"ar_YE","name":"arabcha (Yaman)"},{"code":"hy_AM","name":"armancha (Armaniston)"},{"code":"as_IN","name":"assamcha (Hindiston)"},{"code":"eu_ES","name":"baskcha (Ispaniya)"},{"code":"be_BY","name":"belaruscha (Belorusiya)"},{"code":"bn_BD","name":"bengalcha (Bangladesh)"},{"code":"bn_IN","name":"bengalcha (Hindiston)"},{"code":"my_MM","name":"birmancha (Myanma (Birma))"},{"code":"bg_BG","name":"bolgarcha (Bolgariya)"},{"code":"bs_BA","name":"bosniycha (Bosniya va Gertsegovina)"},{"code":"br_FR","name":"bretoncha (Fransiya)"},{"code":"cs_CZ","name":"chexcha (Chexiya Respublikasi)"},{"code":"da_DK","name":"datcha (Daniya)"},{"code":"da_GL","name":"datcha (Grenlandiya)"},{"code":"et_EE","name":"estoncha (Estoniya)"},{"code":"fo_FO","name":"farercha (Farer orollari)"},{"code":"fi_FI","name":"fincha (Finlyandiya)"},{"code":"fa_AF","name":"forscha (Afg\u02bboniston)"},{"code":"fa_IR","name":"forscha (Eron)"},{"code":"fr_BL","name":"fransuzcha (Avliyo Varfolomey)"},{"code":"fr_BE","name":"fransuzcha (Belgiya)"},{"code":"fr_BJ","name":"fransuzcha (Benin)"},{"code":"fr_BF","name":"fransuzcha (Burkina-Faso)"},{"code":"fr_BI","name":"fransuzcha (Burundi)"},{"code":"fr_TD","name":"fransuzcha (Chad)"},{"code":"fr_DJ","name":"fransuzcha (Djibuti)"},{"code":"fr_GQ","name":"fransuzcha (Ekvatorial Gvineya)"},{"code":"fr_FR","name":"fransuzcha (Fransiya)"},{"code":"fr_GF","name":"fransuzcha (Frantsuz Gvianasi)"},{"code":"fr_PF","name":"fransuzcha (Frantsuz Polineziyasi)"},{"code":"fr_GA","name":"fransuzcha (Gabon)"},{"code":"fr_HT","name":"fransuzcha (Gaiti)"},{"code":"fr_GP","name":"fransuzcha (Gvadelupe)"},{"code":"fr_GN","name":"fransuzcha (Gvineya)"},{"code":"fr_DZ","name":"fransuzcha (Jazoir)"},{"code":"fr_CM","name":"fransuzcha (Kamerun)"},{"code":"fr_CA","name":"fransuzcha (Kanada)"},{"code":"fr_KM","name":"fransuzcha (Komor orollari)"},{"code":"fr_CG","name":"fransuzcha (Kongo Brazzavil)"},{"code":"fr_CD","name":"fransuzcha (Kongo-Kinshasa)"},{"code":"fr_CI","name":"fransuzcha (Kot-d-Ivuar)"},{"code":"fr_LU","name":"fransuzcha (Lyuksemburg)"},{"code":"fr_MG","name":"fransuzcha (Madagaskar)"},{"code":"fr_ML","name":"fransuzcha (Mali)"},{"code":"fr_CF","name":"fransuzcha (Markaziy Afrika Respublikasi)"},{"code":"fr_MA","name":"fransuzcha (Marokash)"},{"code":"fr_MQ","name":"fransuzcha (Martinika)"},{"code":"fr_MU","name":"fransuzcha (Mavrikiy)"},{"code":"fr_MR","name":"fransuzcha (Mavritaniya)"},{"code":"fr_YT","name":"fransuzcha (Mayotta)"},{"code":"fr_MC","name":"fransuzcha (Monako)"},{"code":"fr_NE","name":"fransuzcha (Niger)"},{"code":"fr_RE","name":"fransuzcha (Reyunon)"},{"code":"fr_RW","name":"fransuzcha (Ruanda)"},{"code":"fr_SN","name":"fransuzcha (Senegal)"},{"code":"fr_MF","name":"fransuzcha (Sent-Martin)"},{"code":"fr_PM","name":"fransuzcha (Sent-Pyer va Mikelon)"},{"code":"fr_SC","name":"fransuzcha (Seyshel orollari)"},{"code":"fr_CH","name":"fransuzcha (Shveysariya)"},{"code":"fr_SY","name":"fransuzcha (Suriya)"},{"code":"fr_TG","name":"fransuzcha (Togo)"},{"code":"fr_TN","name":"fransuzcha (Tunis)"},{"code":"fr_WF","name":"fransuzcha (Uellis va Futuna)"},{"code":"fr_VU","name":"fransuzcha (Vanuatu)"},{"code":"fr_NC","name":"fransuzcha (Yangi Kaledoniya)"},{"code":"ff_CM","name":"Fulah (Cameroon)"},{"code":"ff_GN","name":"Fulah (Guinea)"},{"code":"ff_MR","name":"Fulah (Mauritania)"},{"code":"ff_SN","name":"Fulah (Senegal)"},{"code":"gl_ES","name":"galitsiycha (Ispaniya)"},{"code":"lg_UG","name":"gandcha (Uganda)"},{"code":"fy_NL","name":"g\u02bbarbiy friziancha (Niderlandiya)"},{"code":"nl_AW","name":"gollandcha (Aruba)"},{"code":"nl_BE","name":"gollandcha (Belgiya)"},{"code":"nl_BQ","name":"gollandcha (Karib Niderlandiyasi)"},{"code":"nl_CW","name":"gollandcha (Kurasao)"},{"code":"nl_NL","name":"gollandcha (Niderlandiya)"},{"code":"nl_SX","name":"gollandcha (Sint Martin)"},{"code":"nl_SR","name":"gollandcha (Surinam)"},{"code":"ka_GE","name":"gruzincha (Gruziya)"},{"code":"gu_IN","name":"gujoratcha (Hindiston)"},{"code":"hi_IN","name":"hindcha (Hindiston)"},{"code":"he_IL","name":"ibroniy (Isroil)"},{"code":"ig_NG","name":"igbocha (Nigeriya)"},{"code":"id_ID","name":"indoneyzcha (Indoneziya)"},{"code":"en_AS","name":"inglizcha (Amerika Samoasi)"},{"code":"en_AI","name":"inglizcha (Angila)"},{"code":"en_AG","name":"inglizcha (Antigua va Barbados)"},{"code":"en_VI","name":"inglizcha (AQSH Virdjiniya orollari)"},{"code":"en_UM","name":"inglizcha (AQSH yondosh orollari)"},{"code":"en_AU","name":"inglizcha (Avstraliya)"},{"code":"en_BS","name":"inglizcha (Bagama orollari)"},{"code":"en_BB","name":"inglizcha (Barbados)"},{"code":"en_BE","name":"inglizcha (Belgiya)"},{"code":"en_BZ","name":"inglizcha (Beliz)"},{"code":"en_BM","name":"inglizcha (Bermuda)"},{"code":"en_GB","name":"inglizcha (Birlashgan Qirollik)"},{"code":"en_BW","name":"inglizcha (Botsvanna)"},{"code":"en_IO","name":"inglizcha (Britaniya Hind okeani hududi)"},{"code":"en_VG","name":"inglizcha (Britaniya Virdjiniya orollari)"},{"code":"en_DG","name":"inglizcha (Diyego Garsiya)"},{"code":"en_JE","name":"inglizcha (Djersi)"},{"code":"en_DM","name":"inglizcha (Dominika)"},{"code":"en_ER","name":"inglizcha (Eritreya)"},{"code":"en_FJ","name":"inglizcha (Fiji orollari)"},{"code":"en_PH","name":"inglizcha (Filippin)"},{"code":"en_FK","name":"inglizcha (Folklend orollari)"},{"code":"en_GM","name":"inglizcha (Gambiya)"},{"code":"en_GH","name":"inglizcha (Gana)"},{"code":"en_GY","name":"inglizcha (Gayana)"},{"code":"en_GG","name":"inglizcha (Gernsi)"},{"code":"en_GI","name":"inglizcha (Gibraltar)"},{"code":"en_HK","name":"inglizcha (Gonkong Xitoy MMH)"},{"code":"en_GD","name":"inglizcha (Grenada)"},{"code":"en_GU","name":"inglizcha (Guam)"},{"code":"en_IN","name":"inglizcha (Hindiston)"},{"code":"en_IE","name":"inglizcha (Irlandiya)"},{"code":"en_ZA","name":"inglizcha (Janubi-Afrika)"},{"code":"en_SS","name":"inglizcha (Janubiy Sudan)"},{"code":"en_CM","name":"inglizcha (Kamerun)"},{"code":"en_CA","name":"inglizcha (Kanada)"},{"code":"en_KY","name":"inglizcha (Kayman orollari)"},{"code":"en_KE","name":"inglizcha (Keniya)"},{"code":"en_KI","name":"inglizcha (Kiribati)"},{"code":"en_CC","name":"inglizcha (Kokos (Kiling) orollari)"},{"code":"en_CK","name":"inglizcha (Kuk orollari)"},{"code":"en_LS","name":"inglizcha (Lesoto)"},{"code":"en_LR","name":"inglizcha (Liberiya)"},{"code":"en_MG","name":"inglizcha (Madagaskar)"},{"code":"en_MO","name":"inglizcha (Makao Xitoy MMH)"},{"code":"en_MW","name":"inglizcha (Malavi)"},{"code":"en_MY","name":"inglizcha (Malayziya)"},{"code":"en_MT","name":"inglizcha (Malta)"},{"code":"en_MH","name":"inglizcha (Marshal orollari)"},{"code":"en_MU","name":"inglizcha (Mavrikiy)"},{"code":"en_IM","name":"inglizcha (Men oroli)"},{"code":"en_FM","name":"inglizcha (Mikroneziya)"},{"code":"en_MS","name":"inglizcha (Montserrat)"},{"code":"en_SH","name":"inglizcha (Muqaddas Yelena orollari)"},{"code":"en_NA","name":"inglizcha (Namibiya)"},{"code":"en_NR","name":"inglizcha (Nauru)"},{"code":"en_NG","name":"inglizcha (Nigeriya)"},{"code":"en_NU","name":"inglizcha (Niuye)"},{"code":"en_NF","name":"inglizcha (Norfolk orollari)"},{"code":"en_PW","name":"inglizcha (Palau)"},{"code":"en_PG","name":"inglizcha (Papua Yangi Gvineya)"},{"code":"en_PN","name":"inglizcha (Pitkarin orollari)"},{"code":"en_PK","name":"inglizcha (Pokiston)"},{"code":"en_PR","name":"inglizcha (Puerto-Riko)"},{"code":"en_US","name":"inglizcha (Qo\u02bbshma Shtatlar)"},{"code":"en_CX","name":"inglizcha (Rojdestvo oroli)"},{"code":"en_RW","name":"inglizcha (Ruanda)"},{"code":"en_WS","name":"inglizcha (Samoa)"},{"code":"en_KN","name":"inglizcha (Sent-Kits va Nevis)"},{"code":"en_LC","name":"inglizcha (Sent-Lyusiya)"},{"code":"en_VC","name":"inglizcha (Sent-Vinsent va Grenadin)"},{"code":"en_SC","name":"inglizcha (Seyshel orollari)"},{"code":"en_MP","name":"inglizcha (Shimoliy Marianna orollari)"},{"code":"en_SG","name":"inglizcha (Singapur)"},{"code":"en_SX","name":"inglizcha (Sint Martin)"},{"code":"en_SB","name":"inglizcha (Solomon orollari)"},{"code":"en_SD","name":"inglizcha (Sudan)"},{"code":"en_SZ","name":"inglizcha (Svazilend)"},{"code":"en_SL","name":"inglizcha (Syerra-Leone)"},{"code":"en_TZ","name":"inglizcha (Tanzaniya)"},{"code":"en_TK","name":"inglizcha (Tokelau)"},{"code":"en_TO","name":"inglizcha (Tonga)"},{"code":"en_TT","name":"inglizcha (Trinidad va Tobago)"},{"code":"en_TC","name":"inglizcha (Turks va Kaykos orollari)"},{"code":"en_TV","name":"inglizcha (Tuvalu)"},{"code":"en_UG","name":"inglizcha (Uganda)"},{"code":"en_VU","name":"inglizcha (Vanuatu)"},{"code":"en_JM","name":"inglizcha (Yamayka)"},{"code":"en_NZ","name":"inglizcha (Yangi Zelandiya)"},{"code":"en_ZM","name":"inglizcha (Zambiya)"},{"code":"en_ZW","name":"inglizcha (Zimbabve)"},{"code":"ga_IE","name":"irlandcha (Irlandiya)"},{"code":"is_IS","name":"islandcha (Islandiya)"},{"code":"es_AR","name":"ispancha (Argentina)"},{"code":"es_BO","name":"ispancha (Boliviya)"},{"code":"es_CL","name":"ispancha (Chili)"},{"code":"es_DO","name":"ispancha (Dominikan Respublikasi)"},{"code":"es_EC","name":"ispancha (Ekvador)"},{"code":"es_GQ","name":"ispancha (Ekvatorial Gvineya)"},{"code":"es_PH","name":"ispancha (Filippin)"},{"code":"es_HN","name":"ispancha (Gonduras)"},{"code":"es_GT","name":"ispancha (Gvatemala)"},{"code":"es_ES","name":"ispancha (Ispaniya)"},{"code":"es_IC","name":"ispancha (Kanar orollari)"},{"code":"es_CO","name":"ispancha (Kolumbiya)"},{"code":"es_CR","name":"ispancha (Kosta-Rika)"},{"code":"es_CU","name":"ispancha (Kuba)"},{"code":"es_MX","name":"ispancha (Meksika)"},{"code":"es_NI","name":"ispancha (Nikaragua)"},{"code":"es_PA","name":"ispancha (Panama)"},{"code":"es_PY","name":"ispancha (Paragvay)"},{"code":"es_PE","name":"ispancha (Peru)"},{"code":"es_PR","name":"ispancha (Puerto-Riko)"},{"code":"es_US","name":"ispancha (Qo\u02bbshma Shtatlar)"},{"code":"es_SV","name":"ispancha (Salvador)"},{"code":"es_EA","name":"ispancha (Seyta va Melilla)"},{"code":"es_UY","name":"ispancha (Urugvay)"},{"code":"es_VE","name":"ispancha (Venesuela)"},{"code":"it_IT","name":"italyancha (Italiya)"},{"code":"it_SM","name":"italyancha (San-Marino)"},{"code":"it_CH","name":"italyancha (Shveysariya)"},{"code":"ee_GH","name":"ivicha (Gana)"},{"code":"ee_TG","name":"ivicha (Togo)"},{"code":"kl_GL","name":"kalallisutcha (Grenlandiya)"},{"code":"kn_IN","name":"kannadcha (Hindiston)"},{"code":"ks_IN","name":"kashmircha (Hindiston)"},{"code":"ca_AD","name":"katalancha (Andorra)"},{"code":"ca_FR","name":"katalancha (Fransiya)"},{"code":"ca_ES","name":"katalancha (Ispaniya)"},{"code":"ca_IT","name":"katalancha (Italiya)"},{"code":"ki_KE","name":"kikuycha (Keniya)"},{"code":"rw_RW","name":"kinyarvandcha (Ruanda)"},{"code":"ko_KR","name":"koreyscha (Janubiy Koreya)"},{"code":"ko_KP","name":"koreyscha (Shimoliy Koreya)"},{"code":"kw_GB","name":"kornishcha (Birlashgan Qirollik)"},{"code":"lo_LA","name":"laoscha (Laos)"},{"code":"lv_LV","name":"latishcha (Latviya)"},{"code":"ln_AO","name":"lingalcha (Angola)"},{"code":"ln_CG","name":"lingalcha (Kongo Brazzavil)"},{"code":"ln_CD","name":"lingalcha (Kongo-Kinshasa)"},{"code":"ln_CF","name":"lingalcha (Markaziy Afrika Respublikasi)"},{"code":"lt_LT","name":"litovcha (Litva)"},{"code":"lu_CD","name":"luba-katangcha (Kongo-Kinshasa)"},{"code":"lb_LU","name":"lyuksemburgcha (Lyuksemburg)"},{"code":"mk_MK","name":"makedoncha (Makedoniya)"},{"code":"mg_MG","name":"malagasiycha (Madagaskar)"},{"code":"ml_IN","name":"malayamcha (Hindiston)"},{"code":"ms_BN","name":"malaycha (Bruney)"},{"code":"ms_MY","name":"malaycha (Malayziya)"},{"code":"ms_SG","name":"malaycha (Singapur)"},{"code":"mt_MT","name":"maltacha (Malta)"},{"code":"mr_IN","name":"maratcha (Hindiston)"},{"code":"gv_IM","name":"mencha (Men oroli)"},{"code":"mn_MN","name":"mo\u2018g\u2018ulcha (Mo\u2018g\u2018uliston)"},{"code":"de_AT","name":"nemischa (Avstriya)"},{"code":"de_BE","name":"nemischa (Belgiya)"},{"code":"de_DE","name":"nemischa (Germaniya)"},{"code":"de_LI","name":"nemischa (Lixtenshteyn)"},{"code":"de_LU","name":"nemischa (Lyuksemburg)"},{"code":"de_CH","name":"nemischa (Shveysariya)"},{"code":"ne_IN","name":"nepalcha (Hindiston)"},{"code":"ne_NP","name":"nepalcha (Nepal)"},{"code":"nb_NO","name":"norvegcha bokmal (Norvegiya)"},{"code":"nb_SJ","name":"norvegcha bokmal (Savlbard va Jan Mayen)"},{"code":"nn_NO","name":"norvegcha ninorsk (Norvegiya)"},{"code":"no_NO","name":"Norwegian (Norway)"},{"code":"uz_AF","name":"o\u02bbzbekcha (Afg\u02bboniston)"},{"code":"uz_UZ","name":"o\u02bbzbekcha (O\u02bbzbekiston)"},{"code":"or_IN","name":"oriycha (Hindiston)"},{"code":"om_ET","name":"oromocha (Efiopiya)"},{"code":"om_KE","name":"oromocha (Keniya)"},{"code":"os_GE","name":"Ossetic (Georgia)"},{"code":"os_RU","name":"Ossetic (Russia)"},{"code":"az_AZ","name":"ozarbayjoncha (Ozarbayjon)"},{"code":"pa_IN","name":"panjobcha (Hindiston)"},{"code":"pa_PK","name":"panjobcha (Pokiston)"},{"code":"pl_PL","name":"polyakcha (Polsha)"},{"code":"pt_AO","name":"portugalcha (Angola)"},{"code":"pt_BR","name":"portugalcha (Braziliya)"},{"code":"pt_GW","name":"portugalcha (Gvineya-Bisau)"},{"code":"pt_CV","name":"portugalcha (Kabo-Verde)"},{"code":"pt_MO","name":"portugalcha (Makao Xitoy MMH)"},{"code":"pt_MZ","name":"portugalcha (Mozambik)"},{"code":"pt_PT","name":"portugalcha (Portugaliya)"},{"code":"pt_ST","name":"portugalcha (San-Tome va Prinsipi)"},{"code":"pt_TL","name":"portugalcha (Sharqiy-Timor)"},{"code":"ps_AF","name":"pushtu tili (Afg\u02bboniston)"},{"code":"ky_KG","name":"qirg\u02bbizcha (Qirg\u02bbiziston)"},{"code":"kk_KZ","name":"qozoqcha (Qozog\u02bbiston)"},{"code":"qu_BO","name":"qvechuancha (Boliviya)"},{"code":"qu_EC","name":"qvechuancha (Ekvador)"},{"code":"qu_PE","name":"qvechuancha (Peru)"},{"code":"rm_CH","name":"romancha (Shveysariya)"},{"code":"ro_MD","name":"rumincha (Moldova)"},{"code":"ro_RO","name":"rumincha (Ruminiya)"},{"code":"rn_BI","name":"rundcha (Burundi)"},{"code":"ru_BY","name":"ruscha (Belorusiya)"},{"code":"ru_MD","name":"ruscha (Moldova)"},{"code":"ru_KG","name":"ruscha (Qirg\u02bbiziston)"},{"code":"ru_KZ","name":"ruscha (Qozog\u02bbiston)"},{"code":"ru_RU","name":"ruscha (Rossiya)"},{"code":"ru_UA","name":"ruscha (Ukraina)"},{"code":"sg_CF","name":"sangoancha (Markaziy Afrika Respublikasi)"},{"code":"gd_GB","name":"Scottish Gaelic (United Kingdom)"},{"code":"sr_BA","name":"serbcha (Bosniya va Gertsegovina)"},{"code":"sr_ME","name":"serbcha (Chernogoriya)"},{"code":"sr_XK","name":"serbcha (Kosovo)"},{"code":"sr_RS","name":"serbcha (Serbiya)"},{"code":"sh_BA","name":"Serbo-Croatian (Bosnia & Herzegovina)"},{"code":"nd_ZW","name":"shimoliy ndebelcha (Zimbabve)"},{"code":"se_FI","name":"shimoliy semiycha (Finlyandiya)"},{"code":"se_NO","name":"shimoliy semiycha (Norvegiya)"},{"code":"se_SE","name":"shimoliy semiycha (Shvetsiya)"},{"code":"sn_ZW","name":"shoniycha (Zimbabve)"},{"code":"sv_AX","name":"shvedcha (Aland orollari)"},{"code":"sv_FI","name":"shvedcha (Finlyandiya)"},{"code":"sv_SE","name":"shvedcha (Shvetsiya)"},{"code":"si_LK","name":"sinholcha (Shri-Lanka)"},{"code":"sk_SK","name":"slovakcha (Slovakiya)"},{"code":"sl_SI","name":"slovencha (Sloveniya)"},{"code":"so_DJ","name":"somalicha (Djibuti)"},{"code":"so_ET","name":"somalicha (Efiopiya)"},{"code":"so_KE","name":"somalicha (Keniya)"},{"code":"so_SO","name":"somalicha (Somali)"},{"code":"sw_KE","name":"svahilcha (Keniya)"},{"code":"sw_TZ","name":"svahilcha (Tanzaniya)"},{"code":"sw_UG","name":"svahilcha (Uganda)"},{"code":"tl_PH","name":"Tagalog (Philippines)"},{"code":"ta_IN","name":"tamilcha (Hindiston)"},{"code":"ta_MY","name":"tamilcha (Malayziya)"},{"code":"ta_LK","name":"tamilcha (Shri-Lanka)"},{"code":"ta_SG","name":"tamilcha (Singapur)"},{"code":"th_TH","name":"taycha (Tayland)"},{"code":"te_IN","name":"telugvancha (Hindiston)"},{"code":"bo_IN","name":"tibetcha (Hindiston)"},{"code":"bo_CN","name":"tibetcha (Xitoy)"},{"code":"ti_ET","name":"tigrincha (Efiopiya)"},{"code":"ti_ER","name":"tigrincha (Eritreya)"},{"code":"to_TO","name":"tongocha (Tonga)"},{"code":"tr_CY","name":"turkcha (Kipr)"},{"code":"tr_TR","name":"turkcha (Turkiya)"},{"code":"cy_GB","name":"uelscha (Birlashgan Qirollik)"},{"code":"uk_UA","name":"ukraincha (Ukraina)"},{"code":"ur_IN","name":"urducha (Hindiston)"},{"code":"ur_PK","name":"urducha (Pokiston)"},{"code":"ug_CN","name":"uyg\u02bburcha (Xitoy)"},{"code":"hu_HU","name":"vengrcha (Vengriya)"},{"code":"vi_VN","name":"vyetnamcha (Vyetnam)"},{"code":"ha_GH","name":"xauscha (Gana)"},{"code":"ha_NE","name":"xauscha (Niger)"},{"code":"ha_NG","name":"xauscha (Nigeriya)"},{"code":"zh_HK","name":"xitoycha (Gonkong Xitoy MMH)"},{"code":"zh_MO","name":"xitoycha (Makao Xitoy MMH)"},{"code":"zh_SG","name":"xitoycha (Singapur)"},{"code":"zh_TW","name":"xitoycha (Tayvan)"},{"code":"zh_CN","name":"xitoycha (Xitoy)"},{"code":"km_KH","name":"xmercha (Kambodja)"},{"code":"hr_BA","name":"xorvatcha (Bosniya va Gertsegovina)"},{"code":"hr_HR","name":"xorvatcha (Xorvatiya)"},{"code":"ja_JP","name":"yaponcha (Yaponiya)"},{"code":"yo_BJ","name":"yorubcha (Benin)"},{"code":"yo_NG","name":"yorubcha (Nigeriya)"},{"code":"dz_BT","name":"yovoncha (Butan)"},{"code":"el_GR","name":"yunoncha (Gretsiya)"},{"code":"el_CY","name":"yunoncha (Kipr)"},{"code":"ii_CN","name":"zichuan yicha (Xitoy)"},{"code":"zu_ZA","name":"zuluancha (Janubi-Afrika)"}]