[{"code":"af","name":"afrikanerski"},{"code":"ak","name":"akan"},{"code":"sq","name":"albanski"},{"code":"am","name":"amharski"},{"code":"ar","name":"arapski"},{"code":"as","name":"asemijski"},{"code":"az","name":"azerbejd\u017eanski"},{"code":"bm","name":"bambara"},{"code":"eu","name":"baskijski"},{"code":"bn","name":"bengalski"},{"code":"be","name":"bjeloruski"},{"code":"bs","name":"bosanski"},{"code":"br","name":"bretonski"},{"code":"bg","name":"bugarski"},{"code":"my","name":"burmanski"},{"code":"cy","name":"cy"},{"code":"cs","name":"\u010de\u0161ki"},{"code":"da","name":"danski"},{"code":"dz","name":"d\u017eonga"},{"code":"en","name":"engleski"},{"code":"eo","name":"esperanto"},{"code":"et","name":"estonski"},{"code":"ee","name":"eve"},{"code":"fo","name":"farski"},{"code":"fi","name":"finski"},{"code":"fr","name":"francuski"},{"code":"fy","name":"frizijski"},{"code":"ff","name":"fulah"},{"code":"gl","name":"galski"},{"code":"lg","name":"ganda"},{"code":"el","name":"gr\u010dki"},{"code":"ka","name":"gruzijski"},{"code":"gu","name":"gud\u017earati"},{"code":"ha","name":"hausa"},{"code":"he","name":"hebrejski"},{"code":"hi","name":"hindi"},{"code":"nl","name":"holandski"},{"code":"hr","name":"hrvatski"},{"code":"ig","name":"igbo"},{"code":"id","name":"indonezijski"},{"code":"ga","name":"irski"},{"code":"is","name":"islandski"},{"code":"it","name":"italijanski"},{"code":"ja","name":"japanski"},{"code":"hy","name":"jermenski"},{"code":"yi","name":"jidi\u0161"},{"code":"yo","name":"jorubanski"},{"code":"kl","name":"kalalisutski"},{"code":"kn","name":"kanada"},{"code":"ks","name":"ka\u0161miri"},{"code":"ca","name":"katalonski"},{"code":"kk","name":"kaza\u010dki"},{"code":"ki","name":"kikuju"},{"code":"zh","name":"kineski"},{"code":"rw","name":"kinjarvanda"},{"code":"ky","name":"kirgiski"},{"code":"km","name":"kmerski"},{"code":"ko","name":"korejski"},{"code":"kw","name":"korni\u0161ki"},{"code":"qu","name":"kven\u010da"},{"code":"lo","name":"lao\u0161ki"},{"code":"lv","name":"letonski"},{"code":"ln","name":"lingala"},{"code":"lt","name":"litvanski"},{"code":"lu","name":"luba-katanga"},{"code":"lb","name":"luksembur\u0161ki"},{"code":"hu","name":"ma\u0111arski"},{"code":"mk","name":"makedonski"},{"code":"mg","name":"malagazijski"},{"code":"ml","name":"malajalam"},{"code":"ms","name":"malajski"},{"code":"mt","name":"malte\u0161ki"},{"code":"gv","name":"manks"},{"code":"mr","name":"marati"},{"code":"mn","name":"mongolski"},{"code":"ne","name":"nepalski"},{"code":"no","name":"norve\u0161ki"},{"code":"nb","name":"norve\u0161ki bokmal"},{"code":"nn","name":"norve\u0161ki njorsk"},{"code":"de","name":"njema\u010dki"},{"code":"or","name":"orijski"},{"code":"om","name":"oromo"},{"code":"os","name":"osetski"},{"code":"pa","name":"pand\u017eabski"},{"code":"ps","name":"pa\u0161tunski"},{"code":"fa","name":"perzijski"},{"code":"pl","name":"poljski"},{"code":"pt","name":"portugalski"},{"code":"rm","name":"reto-romanski"},{"code":"ro","name":"rumunski"},{"code":"rn","name":"rundi"},{"code":"ru","name":"ruski"},{"code":"sg","name":"sango"},{"code":"ii","name":"si\u010duan ji"},{"code":"si","name":"singaleski"},{"code":"nd","name":"sjeverni ndebele"},{"code":"se","name":"sjeverni sami"},{"code":"sk","name":"slova\u010dki"},{"code":"sl","name":"slovena\u010dki"},{"code":"so","name":"somalski"},{"code":"sr","name":"srpski"},{"code":"sh","name":"srpskohrvatski"},{"code":"sw","name":"svahili"},{"code":"gd","name":"\u0161kotski galski"},{"code":"sn","name":"\u0161ona"},{"code":"es","name":"\u0161panski"},{"code":"sv","name":"\u0161vedski"},{"code":"tl","name":"tagalski"},{"code":"th","name":"tajlandski"},{"code":"ta","name":"tamilski"},{"code":"te","name":"telugu"},{"code":"bo","name":"tibetanski"},{"code":"ti","name":"tigrinja"},{"code":"to","name":"tonga"},{"code":"tr","name":"turski"},{"code":"ug","name":"ujgurski"},{"code":"uk","name":"ukrajinski"},{"code":"ur","name":"urdu"},{"code":"uz","name":"uzbe\u010dki"},{"code":"vi","name":"vijetnamski"},{"code":"zu","name":"zulu"},{"code":"en_SG","name":"engleski (Singapur)"},{"code":"en_SX","name":"engleski (Sint Marten)"},{"code":"en_US","name":"engleski (Sjedinjene Ameri\u010dke Dr\u017eave)"},{"code":"en_MP","name":"engleski (Sjeverna Marijanska Ostrva)"},{"code":"en_SB","name":"engleski (Solomonska Ostrva)"},{"code":"en_SD","name":"engleski (Sudan)"},{"code":"en_SZ","name":"engleski (Svazilend)"},{"code":"en_SH","name":"engleski (Sveta Helena)"},{"code":"en_TZ","name":"engleski (Tanzanija)"},{"code":"en_TK","name":"engleski (Tokelau)"},{"code":"en_TO","name":"engleski (Tonga)"},{"code":"en_TT","name":"engleski (Trinidad i Tobago)"},{"code":"en_TC","name":"engleski (Turks i Kajkos Ostrva)"},{"code":"en_TV","name":"engleski (Tuvalu)"},{"code":"en_UG","name":"engleski (Uganda)"},{"code":"en_VU","name":"engleski (Vanuatu)"},{"code":"en_GB","name":"engleski (Velika Britanija)"},{"code":"en_ZM","name":"engleski (Zambija)"},{"code":"en_ZW","name":"engleski (Zimbabve)"},{"code":"et_EE","name":"estonski (Estonija)"},{"code":"ee_GH","name":"eve (Gana)"},{"code":"ee_TG","name":"eve (Togo)"},{"code":"fo_FO","name":"farski (Farska Ostrva)"},{"code":"fi_FI","name":"finski (Finska)"},{"code":"fr_DZ","name":"francuski (Al\u017eir)"},{"code":"fr_BE","name":"francuski (Belgija)"},{"code":"fr_BJ","name":"francuski (Benin)"},{"code":"fr_BF","name":"francuski (Burkina Faso)"},{"code":"fr_BI","name":"francuski (Burundi)"},{"code":"fr_CF","name":"francuski (Centralnoafri\u010dka Republika)"},{"code":"fr_TD","name":"francuski (\u010cad)"},{"code":"fr_CD","name":"francuski (Demokratska Republika Kongo)"},{"code":"fr_DJ","name":"francuski (D\u017eibuti)"},{"code":"fr_GQ","name":"francuski (Ekvatorijalna Gvineja)"},{"code":"fr_GF","name":"francuski (Francuska Gvajana)"},{"code":"fr_PF","name":"francuski (Francuska Polinezija)"},{"code":"fr_FR","name":"francuski (Francuska)"},{"code":"fr_GA","name":"francuski (Gabon)"},{"code":"fr_GP","name":"francuski (Gvadelupe)"},{"code":"fr_GN","name":"francuski (Gvineja)"},{"code":"fr_HT","name":"francuski (Haiti)"},{"code":"fr_CM","name":"francuski (Kamerun)"},{"code":"fr_CA","name":"francuski (Kanada)"},{"code":"fr_KM","name":"francuski (Komorska Ostrva)"},{"code":"fr_CG","name":"francuski (Kongo)"},{"code":"fr_LU","name":"francuski (Luksemburg)"},{"code":"fr_MG","name":"francuski (Madagaskar)"},{"code":"fr_YT","name":"francuski (Majote)"},{"code":"fr_ML","name":"francuski (Mali)"},{"code":"fr_MA","name":"francuski (Maroko)"},{"code":"fr_MQ","name":"francuski (Martinik)"},{"code":"fr_MU","name":"francuski (Mauricius)"},{"code":"fr_MR","name":"francuski (Mauritanija)"},{"code":"fr_MC","name":"francuski (Monako)"},{"code":"fr_NE","name":"francuski (Niger)"},{"code":"fr_NC","name":"francuski (Nova Kaledonija)"},{"code":"fr_CI","name":"francuski (Obala Slonova\u010de)"},{"code":"fr_RE","name":"francuski (Rejunion)"},{"code":"fr_RW","name":"francuski (Ruanda)"},{"code":"fr_SC","name":"francuski (Sej\u0161eli)"},{"code":"fr_PM","name":"francuski (Sen Pjer i Mikelon)"},{"code":"fr_SN","name":"francuski (Senegal)"},{"code":"fr_SY","name":"francuski (Sirija)"},{"code":"fr_BL","name":"francuski (Sv. Bartolomej)"},{"code":"fr_MF","name":"francuski (Sv. Martin)"},{"code":"fr_CH","name":"francuski (\u0160vicarska)"},{"code":"fr_TG","name":"francuski (Togo)"},{"code":"fr_TN","name":"francuski (Tunis)"},{"code":"fr_WF","name":"francuski (Valis i Futuna Ostrva)"},{"code":"fr_VU","name":"francuski (Vanuatu)"},{"code":"fy_NL","name":"frizijski (Holandija)"},{"code":"ff_GN","name":"fulah (Gvineja)"},{"code":"ff_CM","name":"fulah (Kamerun)"},{"code":"ff_MR","name":"fulah (Mauritanija)"},{"code":"ff_SN","name":"fulah (Senegal)"},{"code":"gl_ES","name":"galski (\u0160panija)"},{"code":"lg_UG","name":"ganda (Uganda)"},{"code":"el_GR","name":"gr\u010dki (Gr\u010dka)"},{"code":"el_CY","name":"gr\u010dki (Kipar)"},{"code":"ka_GE","name":"gruzijski (Gruzija)"},{"code":"gu_IN","name":"gud\u017earati (Indija)"},{"code":"ha_GH","name":"hausa (Gana)"},{"code":"ha_NE","name":"hausa (Niger)"},{"code":"ha_NG","name":"hausa (Nigerija)"},{"code":"he_IL","name":"hebrejski (Izrael)"},{"code":"hi_IN","name":"hindi (Indija)"},{"code":"nl_AW","name":"holandski (Aruba)"},{"code":"nl_BE","name":"holandski (Belgija)"},{"code":"nl_NL","name":"holandski (Holandija)"},{"code":"nl_BQ","name":"holandski (Karipska Holandija)"},{"code":"nl_CW","name":"holandski (Kurasao)"},{"code":"nl_SX","name":"holandski (Sint Marten)"},{"code":"nl_SR","name":"holandski (Surinam)"},{"code":"hr_BA","name":"hrvatski (Bosna i Hercegovina)"},{"code":"hr_HR","name":"hrvatski (Hrvatska)"},{"code":"ig_NG","name":"igbo (Nigerija)"},{"code":"id_ID","name":"indonezijski (Indonezija)"},{"code":"ga_IE","name":"irski (Irska)"},{"code":"is_IS","name":"islandski (Island)"},{"code":"it_IT","name":"italijanski (Italija)"},{"code":"it_SM","name":"italijanski (San Marino)"},{"code":"it_CH","name":"italijanski (\u0160vicarska)"},{"code":"ja_JP","name":"japanski (Japan)"},{"code":"hy_AM","name":"jermenski (Jermenija)"},{"code":"yo_BJ","name":"jorubanski (Benin)"},{"code":"yo_NG","name":"jorubanski (Nigerija)"},{"code":"kl_GL","name":"kalalisutski (Grenland)"},{"code":"kn_IN","name":"kanada (Indija)"},{"code":"ks_IN","name":"ka\u0161miri (Indija)"},{"code":"ca_AD","name":"katalonski (Andora)"},{"code":"ca_FR","name":"katalonski (Francuska)"},{"code":"ca_IT","name":"katalonski (Italija)"},{"code":"ca_ES","name":"katalonski (\u0160panija)"},{"code":"kk_KZ","name":"kaza\u010dki (Kazahstan)"},{"code":"ki_KE","name":"kikuju (Kenija)"},{"code":"zh_HK","name":"kineski (Hong Kong (S. A. R. Kina))"},{"code":"zh_CN","name":"kineski (Kina)"},{"code":"zh_MO","name":"kineski (Makao (S. A. R. Kina))"},{"code":"zh_SG","name":"kineski (Singapur)"},{"code":"zh_TW","name":"kineski (Tajvan)"},{"code":"rw_RW","name":"kinjarvanda (Ruanda)"},{"code":"ky_KG","name":"kirgiski (Kirgizstan)"},{"code":"km_KH","name":"kmerski (Kambod\u017ea)"},{"code":"ko_KR","name":"korejski (Ju\u017ena Koreja)"},{"code":"ko_KP","name":"korejski (Sjeverna Koreja)"},{"code":"kw_GB","name":"korni\u0161ki (Velika Britanija)"},{"code":"qu_BO","name":"kven\u010da (Bolivija)"},{"code":"qu_EC","name":"kven\u010da (Ekvador)"},{"code":"qu_PE","name":"kven\u010da (Peru)"},{"code":"lo_LA","name":"lao\u0161ki (Laos)"},{"code":"lv_LV","name":"letonski (Letonija)"},{"code":"ln_AO","name":"lingala (Angola)"},{"code":"ln_CF","name":"lingala (Centralnoafri\u010dka Republika)"},{"code":"ln_CD","name":"lingala (Demokratska Republika Kongo)"},{"code":"ln_CG","name":"lingala (Kongo)"},{"code":"lt_LT","name":"litvanski (Litvanija)"},{"code":"lu_CD","name":"luba-katanga (Demokratska Republika Kongo)"},{"code":"lb_LU","name":"luksembur\u0161ki (Luksemburg)"},{"code":"hu_HU","name":"ma\u0111arski (Ma\u0111arska)"},{"code":"mk_MK","name":"makedonski (Makedonija)"},{"code":"mg_MG","name":"malagazijski (Madagaskar)"},{"code":"ml_IN","name":"malajalam (Indija)"},{"code":"ms_BN","name":"malajski (Brunej)"},{"code":"ms_MY","name":"malajski (Malezija)"},{"code":"ms_SG","name":"malajski (Singapur)"},{"code":"mt_MT","name":"malte\u0161ki (Malta)"},{"code":"gv_IM","name":"manks (Ostrvo Man)"},{"code":"mr_IN","name":"marati (Indija)"},{"code":"mn_MN","name":"mongolski (Mongolija)"},{"code":"ne_IN","name":"nepalski (Indija)"},{"code":"ne_NP","name":"nepalski (Nepal)"},{"code":"no_NO","name":"norve\u0161ki (Norve\u0161ka)"},{"code":"nb_NO","name":"norve\u0161ki bokmal (Norve\u0161ka)"},{"code":"nb_SJ","name":"norve\u0161ki bokmal (Svalbard i Janmajen Ostrva)"},{"code":"nn_NO","name":"norve\u0161ki njorsk (Norve\u0161ka)"},{"code":"de_AT","name":"njema\u010dki (Austrija)"},{"code":"de_BE","name":"njema\u010dki (Belgija)"},{"code":"de_LI","name":"njema\u010dki (Lihten\u0161tajn)"},{"code":"de_LU","name":"njema\u010dki (Luksemburg)"},{"code":"de_DE","name":"njema\u010dki (Njema\u010dka)"},{"code":"de_CH","name":"njema\u010dki (\u0160vicarska)"},{"code":"or_IN","name":"orijski (Indija)"},{"code":"om_ET","name":"oromo (Etiopija)"},{"code":"om_KE","name":"oromo (Kenija)"},{"code":"os_GE","name":"osetski (Gruzija)"},{"code":"os_RU","name":"osetski (Rusija)"},{"code":"pa_IN","name":"pand\u017eabski (Indija)"},{"code":"pa_PK","name":"pand\u017eabski (Pakistan)"},{"code":"ps_AF","name":"pa\u0161tunski (Afganistan)"},{"code":"fa_AF","name":"perzijski (Afganistan)"},{"code":"fa_IR","name":"perzijski (Iran)"},{"code":"pl_PL","name":"poljski (Poljska)"},{"code":"pt_AO","name":"portugalski (Angola)"},{"code":"pt_BR","name":"portugalski (Brazil)"},{"code":"pt_GW","name":"portugalski (Gvineja-Bisao)"},{"code":"pt_CV","name":"portugalski (Kape Verde)"},{"code":"pt_MO","name":"portugalski (Makao (S. A. R. Kina))"},{"code":"pt_MZ","name":"portugalski (Mozambik)"},{"code":"pt_PT","name":"portugalski (Portugal)"},{"code":"pt_ST","name":"portugalski (Sao Tome i Principe)"},{"code":"pt_TL","name":"portugalski (Timor Leste)"},{"code":"rm_CH","name":"reto-romanski (\u0160vicarska)"},{"code":"ro_MD","name":"rumunski (Moldavija)"},{"code":"ro_RO","name":"rumunski (Rumunija)"},{"code":"rn_BI","name":"rundi (Burundi)"},{"code":"ru_BY","name":"ruski (Bjelorusija)"},{"code":"ru_KZ","name":"ruski (Kazahstan)"},{"code":"ru_KG","name":"ruski (Kirgizstan)"},{"code":"ru_MD","name":"ruski (Moldavija)"},{"code":"ru_RU","name":"ruski (Rusija)"},{"code":"ru_UA","name":"ruski (Ukrajina)"},{"code":"sg_CF","name":"sango (Centralnoafri\u010dka Republika)"},{"code":"ii_CN","name":"si\u010duan ji (Kina)"},{"code":"si_LK","name":"singaleski (\u0160ri Lanka)"},{"code":"nd_ZW","name":"sjeverni ndebele (Zimbabve)"},{"code":"se_FI","name":"sjeverni sami (Finska)"},{"code":"se_NO","name":"sjeverni sami (Norve\u0161ka)"},{"code":"se_SE","name":"sjeverni sami (\u0160vedska)"},{"code":"sk_SK","name":"slova\u010dki (Slova\u010dka)"},{"code":"sl_SI","name":"slovena\u010dki (Slovenija)"},{"code":"so_DJ","name":"somalski (D\u017eibuti)"},{"code":"so_ET","name":"somalski (Etiopija)"},{"code":"so_KE","name":"somalski (Kenija)"},{"code":"so_SO","name":"somalski (Somalija)"},{"code":"sr_BA","name":"srpski (Bosna i Hercegovina)"},{"code":"sr_ME","name":"srpski (Crna Gora)"},{"code":"sr_XK","name":"srpski (Kosovo)"},{"code":"sr_RS","name":"srpski (Srbija)"},{"code":"sh_BA","name":"srpskohrvatski (Bosna i Hercegovina)"},{"code":"sw_KE","name":"svahili (Kenija)"},{"code":"sw_TZ","name":"svahili (Tanzanija)"},{"code":"sw_UG","name":"svahili (Uganda)"},{"code":"gd_GB","name":"\u0161kotski galski (Velika Britanija)"},{"code":"sn_ZW","name":"\u0161ona (Zimbabve)"},{"code":"es_AR","name":"\u0161panski (Argentina)"},{"code":"es_BO","name":"\u0161panski (Bolivija)"},{"code":"es_CL","name":"\u0161panski (\u010cile)"},{"code":"es_DO","name":"\u0161panski (Dominikanska Republika)"},{"code":"es_EC","name":"\u0161panski (Ekvador)"},{"code":"es_GQ","name":"\u0161panski (Ekvatorijalna Gvineja)"},{"code":"es_PH","name":"\u0161panski (Filipini)"},{"code":"es_GT","name":"\u0161panski (Gvatemala)"},{"code":"es_HN","name":"\u0161panski (Honduras)"},{"code":"es_IC","name":"\u0161panski (Kanarska ostrva)"},{"code":"es_CO","name":"\u0161panski (Kolumbija)"},{"code":"es_CR","name":"\u0161panski (Kostarika)"},{"code":"es_CU","name":"\u0161panski (Kuba)"},{"code":"es_MX","name":"\u0161panski (Meksiko)"},{"code":"es_NI","name":"\u0161panski (Nikaragva)"},{"code":"es_PA","name":"\u0161panski (Panama)"},{"code":"es_PY","name":"\u0161panski (Paragvaj)"},{"code":"es_PE","name":"\u0161panski (Peru)"},{"code":"es_PR","name":"\u0161panski (Porto Riko)"},{"code":"es_SV","name":"\u0161panski (Salvador)"},{"code":"es_EA","name":"\u0161panski (Seuta i Melilja)"},{"code":"es_US","name":"\u0161panski (Sjedinjene Ameri\u010dke Dr\u017eave)"},{"code":"es_ES","name":"\u0161panski (\u0160panija)"},{"code":"es_UY","name":"\u0161panski (Urugvaj)"},{"code":"es_VE","name":"\u0161panski (Venecuela)"},{"code":"sv_AX","name":"\u0161vedski (Alandska Ostrva)"},{"code":"sv_FI","name":"\u0161vedski (Finska)"},{"code":"sv_SE","name":"\u0161vedski (\u0160vedska)"},{"code":"tl_PH","name":"tagalski (Filipini)"},{"code":"th_TH","name":"tajlandski (Tajland)"},{"code":"ta_IN","name":"tamilski (Indija)"},{"code":"ta_MY","name":"tamilski (Malezija)"},{"code":"ta_SG","name":"tamilski (Singapur)"},{"code":"ta_LK","name":"tamilski (\u0160ri Lanka)"},{"code":"te_IN","name":"telugu (Indija)"},{"code":"bo_IN","name":"tibetanski (Indija)"},{"code":"bo_CN","name":"tibetanski (Kina)"},{"code":"ti_ER","name":"tigrinja (Eritreja)"},{"code":"ti_ET","name":"tigrinja (Etiopija)"},{"code":"to_TO","name":"tonga (Tonga)"},{"code":"tr_CY","name":"turski (Kipar)"},{"code":"tr_TR","name":"turski (Turska)"},{"code":"ug_CN","name":"ujgurski (Kina)"},{"code":"uk_UA","name":"ukrajinski (Ukrajina)"},{"code":"ur_IN","name":"urdu (Indija)"},{"code":"ur_PK","name":"urdu (Pakistan)"},{"code":"uz_AF","name":"uzbe\u010dki (Afganistan)"},{"code":"uz_UZ","name":"uzbe\u010dki (Uzbekistan)"},{"code":"vi_VN","name":"vijetnamski (Vijetnam)"},{"code":"zu_ZA","name":"zulu (Ju\u017enoafri\u010dka Republika)"}]