[{"code":"AF","name":"Afganistan"},{"code":"AX","name":"Alandska Ostrva"},{"code":"AL","name":"Albanija"},{"code":"DZ","name":"Al\u017eir"},{"code":"AS","name":"Ameri\u010dka Samoa"},{"code":"AD","name":"Andora"},{"code":"AO","name":"Angola"},{"code":"AI","name":"Angvila"},{"code":"AQ","name":"Antarktika"},{"code":"AG","name":"Antigva i Barbuda"},{"code":"AR","name":"Argentina"},{"code":"AW","name":"Aruba"},{"code":"AU","name":"Australija"},{"code":"AT","name":"Austrija"},{"code":"AZ","name":"Azerbejd\u017ean"},{"code":"BS","name":"Bahami"},{"code":"BH","name":"Bahrein"},{"code":"BD","name":"Banglade\u0161"},{"code":"BB","name":"Barbados"},{"code":"BE","name":"Belgija"},{"code":"BZ","name":"Belize"},{"code":"BJ","name":"Benin"},{"code":"BM","name":"Bermuda"},{"code":"BY","name":"Bjelorusija"},{"code":"BW","name":"Bocvana"},{"code":"BO","name":"Bolivija"},{"code":"BA","name":"Bosna i Hercegovina"},{"code":"CX","name":"Bo\u017ei\u0107na Ostrva"},{"code":"BR","name":"Brazil"},{"code":"VG","name":"Britanska Djevi\u010danska Ostrva"},{"code":"IO","name":"Britanska Territorija u Indijskom Okeanu"},{"code":"BN","name":"Brunej"},{"code":"BG","name":"Bugarska"},{"code":"BF","name":"Burkina Faso"},{"code":"BI","name":"Burundi"},{"code":"BT","name":"Butan"},{"code":"CF","name":"Centralnoafri\u010dka Republika"},{"code":"ME","name":"Crna Gora"},{"code":"TD","name":"\u010cad"},{"code":"CZ","name":"\u010ce\u0161ka"},{"code":"CL","name":"\u010cile"},{"code":"DK","name":"Danska"},{"code":"CD","name":"Demokratska Republika Kongo"},{"code":"DG","name":"Dijego Garsija"},{"code":"VI","name":"Djevi\u010danska Ostrva SAD"},{"code":"DM","name":"Dominika"},{"code":"DO","name":"Dominikanska Republika"},{"code":"JE","name":"D\u017eersi"},{"code":"DJ","name":"D\u017eibuti"},{"code":"EG","name":"Egipat"},{"code":"EC","name":"Ekvador"},{"code":"GQ","name":"Ekvatorijalna Gvineja"},{"code":"ER","name":"Eritreja"},{"code":"EE","name":"Estonija"},{"code":"ET","name":"Etiopija"},{"code":"FO","name":"Farska Ostrva"},{"code":"FJ","name":"Fid\u017ei"},{"code":"PH","name":"Filipini"},{"code":"FI","name":"Finska"},{"code":"FK","name":"Folklandska Ostrva"},{"code":"FR","name":"Francuska"},{"code":"GF","name":"Francuska Gvajana"},{"code":"PF","name":"Francuska Polinezija"},{"code":"TF","name":"Francuske Ju\u017ene Teritorije"},{"code":"GA","name":"Gabon"},{"code":"GM","name":"Gambija"},{"code":"GH","name":"Gana"},{"code":"GG","name":"Gernzi"},{"code":"GI","name":"Gibraltar"},{"code":"GR","name":"Gr\u010dka"},{"code":"GD","name":"Grenada"},{"code":"GL","name":"Grenland"},{"code":"GE","name":"Gruzija"},{"code":"GU","name":"Guam"},{"code":"GP","name":"Gvadelupe"},{"code":"GY","name":"Gvajana"},{"code":"GT","name":"Gvatemala"},{"code":"GN","name":"Gvineja"},{"code":"GW","name":"Gvineja-Bisao"},{"code":"HT","name":"Haiti"},{"code":"NL","name":"Holandija"},{"code":"HN","name":"Honduras"},{"code":"HK","name":"Hong Kong (S. A. R. Kina)"},{"code":"HR","name":"Hrvatska"},{"code":"IN","name":"Indija"},{"code":"ID","name":"Indonezija"},{"code":"IQ","name":"Irak"},{"code":"IR","name":"Iran"},{"code":"IE","name":"Irska"},{"code":"IS","name":"Island"},{"code":"IT","name":"Italija"},{"code":"IL","name":"Izrael"},{"code":"JM","name":"Jamajka"},{"code":"JP","name":"Japan"},{"code":"YE","name":"Jemen"},{"code":"AM","name":"Jermenija"},{"code":"JO","name":"Jordan"},{"code":"GS","name":"Ju\u017ena D\u017eord\u017eija i Ju\u017ena Sendvi\u010d Ostrva"},{"code":"KR","name":"Ju\u017ena Koreja"},{"code":"SS","name":"Ju\u017eni Sudan"},{"code":"ZA","name":"Ju\u017enoafri\u010dka Republika"},{"code":"KY","name":"Kajmanska Ostrva"},{"code":"KH","name":"Kambod\u017ea"},{"code":"CM","name":"Kamerun"},{"code":"CA","name":"Kanada"},{"code":"IC","name":"Kanarska ostrva"},{"code":"CV","name":"Kape Verde"},{"code":"BQ","name":"Karipska Holandija"},{"code":"QA","name":"Katar"},{"code":"KZ","name":"Kazahstan"},{"code":"KE","name":"Kenija"},{"code":"CN","name":"Kina"},{"code":"CY","name":"Kipar"},{"code":"KG","name":"Kirgizstan"},{"code":"KI","name":"Kiribati"},{"code":"CC","name":"Kokos (Keling) Ostrva"},{"code":"CO","name":"Kolumbija"},{"code":"KM","name":"Komorska Ostrva"},{"code":"CG","name":"Kongo"},{"code":"XK","name":"Kosovo"},{"code":"CR","name":"Kostarika"},{"code":"CU","name":"Kuba"},{"code":"CK","name":"Kukova Ostrva"},{"code":"CW","name":"Kurasao"},{"code":"KW","name":"Kuvajt"},{"code":"LA","name":"Laos"},{"code":"LS","name":"Lesoto"},{"code":"LV","name":"Letonija"},{"code":"LB","name":"Liban"},{"code":"LR","name":"Liberija"},{"code":"LY","name":"Libija"},{"code":"LI","name":"Lihten\u0161tajn"},{"code":"LT","name":"Litvanija"},{"code":"LU","name":"Luksemburg"},{"code":"MG","name":"Madagaskar"},{"code":"HU","name":"Ma\u0111arska"},{"code":"YT","name":"Majote"},{"code":"MO","name":"Makao (S. A. R. Kina)"},{"code":"MK","name":"Makedonija"},{"code":"MW","name":"Malavi"},{"code":"MV","name":"Maldivi"},{"code":"MY","name":"Malezija"},{"code":"ML","name":"Mali"},{"code":"MT","name":"Malta"},{"code":"UM","name":"Manja Udaljena Ostrva SAD"},{"code":"MA","name":"Maroko"},{"code":"MH","name":"Mar\u0161alska Ostrva"},{"code":"MQ","name":"Martinik"},{"code":"MU","name":"Mauricius"},{"code":"MR","name":"Mauritanija"},{"code":"MX","name":"Meksiko"},{"code":"MM","name":"Mijanmar"},{"code":"FM","name":"Mikronezija"},{"code":"MD","name":"Moldavija"},{"code":"MC","name":"Monako"},{"code":"MN","name":"Mongolija"},{"code":"MS","name":"Monserat"},{"code":"MZ","name":"Mozambik"},{"code":"NA","name":"Namibija"},{"code":"NR","name":"Nauru"},{"code":"NP","name":"Nepal"},{"code":"NE","name":"Niger"},{"code":"NG","name":"Nigerija"},{"code":"NI","name":"Nikaragva"},{"code":"NU","name":"Niue"},{"code":"NF","name":"Norfolk Ostrvo"},{"code":"NO","name":"Norve\u0161ka"},{"code":"NC","name":"Nova Kaledonija"},{"code":"NZ","name":"Novi Zeland"},{"code":"DE","name":"Njema\u010dka"},{"code":"CI","name":"Obala Slonova\u010de"},{"code":"OM","name":"Oman"},{"code":"AC","name":"Ostrvo Asension"},{"code":"IM","name":"Ostrvo Man"},{"code":"PK","name":"Pakistan"},{"code":"PW","name":"Palau"},{"code":"PS","name":"Palestinska Teritorija"},{"code":"PA","name":"Panama"},{"code":"PG","name":"Papua Nova Gvineja"},{"code":"PY","name":"Paragvaj"},{"code":"PE","name":"Peru"},{"code":"PN","name":"Pitkern"},{"code":"PL","name":"Poljska"},{"code":"PR","name":"Porto Riko"},{"code":"PT","name":"Portugal"},{"code":"RE","name":"Rejunion"},{"code":"RW","name":"Ruanda"},{"code":"RO","name":"Rumunija"},{"code":"RU","name":"Rusija"},{"code":"SV","name":"Salvador"},{"code":"WS","name":"Samoa"},{"code":"SM","name":"San Marino"},{"code":"ST","name":"Sao Tome i Principe"},{"code":"SA","name":"Saudijska Arabija"},{"code":"SC","name":"Sej\u0161eli"},{"code":"PM","name":"Sen Pjer i Mikelon"},{"code":"SN","name":"Senegal"},{"code":"KN","name":"Sent Kits i Nevis"},{"code":"LC","name":"Sent Lucija"},{"code":"VC","name":"Sent Vinsent i Grenadini"},{"code":"EA","name":"Seuta i Melilja"},{"code":"SL","name":"Sijera Leone"},{"code":"SG","name":"Singapur"},{"code":"SX","name":"Sint Marten"},{"code":"SY","name":"Sirija"},{"code":"US","name":"Sjedinjene Ameri\u010dke Dr\u017eave"},{"code":"KP","name":"Sjeverna Koreja"},{"code":"MP","name":"Sjeverna Marijanska Ostrva"},{"code":"SK","name":"Slova\u010dka"},{"code":"SI","name":"Slovenija"},{"code":"SB","name":"Solomonska Ostrva"},{"code":"SO","name":"Somalija"},{"code":"RS","name":"Srbija"},{"code":"SD","name":"Sudan"},{"code":"SR","name":"Surinam"},{"code":"BL","name":"Sv. Bartolomej"},{"code":"MF","name":"Sv. Martin"},{"code":"SJ","name":"Svalbard i Janmajen Ostrva"},{"code":"SZ","name":"Svazilend"},{"code":"SH","name":"Sveta Helena"},{"code":"ES","name":"\u0160panija"},{"code":"LK","name":"\u0160ri Lanka"},{"code":"SE","name":"\u0160vedska"},{"code":"CH","name":"\u0160vicarska"},{"code":"TJ","name":"Tad\u017eikistan"},{"code":"TH","name":"Tajland"},{"code":"TW","name":"Tajvan"},{"code":"TZ","name":"Tanzanija"},{"code":"TL","name":"Timor Leste"},{"code":"TG","name":"Togo"},{"code":"TK","name":"Tokelau"},{"code":"TO","name":"Tonga"},{"code":"TT","name":"Trinidad i Tobago"},{"code":"TA","name":"Tristan da Kunja"},{"code":"TN","name":"Tunis"},{"code":"TM","name":"Turkmenistan"},{"code":"TC","name":"Turks i Kajkos Ostrva"},{"code":"TR","name":"Turska"},{"code":"TV","name":"Tuvalu"},{"code":"UG","name":"Uganda"},{"code":"AE","name":"Ujedinjeni Arapski Emirati"},{"code":"UA","name":"Ukrajina"},{"code":"UY","name":"Urugvaj"},{"code":"UZ","name":"Uzbekistan"},{"code":"WF","name":"Valis i Futuna Ostrva"},{"code":"VU","name":"Vanuatu"},{"code":"VA","name":"Vatikan"},{"code":"GB","name":"Velika Britanija"},{"code":"VE","name":"Venecuela"},{"code":"VN","name":"Vijetnam"},{"code":"ZM","name":"Zambija"},{"code":"EH","name":"Zapadna Sahara"},{"code":"ZW","name":"Zimbabve"}]