[{"code":"AF","name":"Afghanistan"},{"code":"ZA","name":"Afrique du Sud"},{"code":"AL","name":"Albanie"},{"code":"DZ","name":"Alg\u00e9rie"},{"code":"DE","name":"Allemagne"},{"code":"AD","name":"Andorre"},{"code":"AO","name":"Angola"},{"code":"AI","name":"Anguilla"},{"code":"AQ","name":"Antarctique"},{"code":"AG","name":"Antigua-et-Barbuda"},{"code":"SA","name":"Arabie saoudite"},{"code":"AR","name":"Argentine"},{"code":"AM","name":"Arm\u00e9nie"},{"code":"AW","name":"Aruba"},{"code":"AU","name":"Australie"},{"code":"AT","name":"Autriche"},{"code":"AZ","name":"Azerba\u00efdjan"},{"code":"BS","name":"Bahamas"},{"code":"BH","name":"Bahre\u00efn"},{"code":"BD","name":"Bangladesh"},{"code":"BB","name":"Barbade"},{"code":"BE","name":"Belgique"},{"code":"BZ","name":"Belize"},{"code":"BJ","name":"B\u00e9nin"},{"code":"BM","name":"Bermudes"},{"code":"BT","name":"Bhoutan"},{"code":"BY","name":"Bi\u00e9lorussie"},{"code":"BO","name":"Bolivie"},{"code":"BA","name":"Bosnie-Herz\u00e9govine"},{"code":"BW","name":"Botswana"},{"code":"BR","name":"Br\u00e9sil"},{"code":"BN","name":"Brun\u00e9i Darussalam"},{"code":"BG","name":"Bulgarie"},{"code":"BF","name":"Burkina Faso"},{"code":"BI","name":"Burundi"},{"code":"KH","name":"Cambodge"},{"code":"CM","name":"Cameroun"},{"code":"CA","name":"Canada"},{"code":"CV","name":"Cap-Vert"},{"code":"EA","name":"Ceuta et Melilla"},{"code":"CL","name":"Chili"},{"code":"CN","name":"Chine"},{"code":"CY","name":"Chypre"},{"code":"CO","name":"Colombie"},{"code":"KM","name":"Comores"},{"code":"CG","name":"Congo-Brazzaville"},{"code":"CD","name":"Congo-Kinshasa"},{"code":"KP","name":"Cor\u00e9e du Nord"},{"code":"KR","name":"Cor\u00e9e du Sud"},{"code":"CR","name":"Costa Rica"},{"code":"CI","name":"C\u00f4te d\u2019Ivoire"},{"code":"HR","name":"Croatie"},{"code":"CU","name":"Cuba"},{"code":"CW","name":"Cura\u00e7ao"},{"code":"DK","name":"Danemark"},{"code":"DG","name":"Diego Garcia"},{"code":"DJ","name":"Djibouti"},{"code":"DM","name":"Dominique"},{"code":"EG","name":"\u00c9gypte"},{"code":"SV","name":"El Salvador"},{"code":"AE","name":"\u00c9mirats arabes unis"},{"code":"EC","name":"\u00c9quateur"},{"code":"ER","name":"\u00c9rythr\u00e9e"},{"code":"ES","name":"Espagne"},{"code":"EE","name":"Estonie"},{"code":"VA","name":"\u00c9tat de la Cit\u00e9 du Vatican"},{"code":"FM","name":"\u00c9tats f\u00e9d\u00e9r\u00e9s de Micron\u00e9sie"},{"code":"US","name":"\u00c9tats-Unis"},{"code":"ET","name":"\u00c9thiopie"},{"code":"FJ","name":"Fidji"},{"code":"FI","name":"Finlande"},{"code":"FR","name":"France"},{"code":"GA","name":"Gabon"},{"code":"GM","name":"Gambie"},{"code":"GE","name":"G\u00e9orgie"},{"code":"GH","name":"Ghana"},{"code":"GI","name":"Gibraltar"},{"code":"GR","name":"Gr\u00e8ce"},{"code":"GD","name":"Grenade"},{"code":"GL","name":"Groenland"},{"code":"GP","name":"Guadeloupe"},{"code":"GU","name":"Guam"},{"code":"GT","name":"Guatemala"},{"code":"GG","name":"Guernesey"},{"code":"GN","name":"Guin\u00e9e"},{"code":"GQ","name":"Guin\u00e9e \u00e9quatoriale"},{"code":"GW","name":"Guin\u00e9e-Bissau"},{"code":"GY","name":"Guyana"},{"code":"GF","name":"Guyane fran\u00e7aise"},{"code":"HT","name":"Ha\u00efti"},{"code":"HN","name":"Honduras"},{"code":"HU","name":"Hongrie"},{"code":"CX","name":"\u00cele Christmas"},{"code":"AC","name":"\u00cele de l\u2019Ascension"},{"code":"IM","name":"\u00cele de Man"},{"code":"NF","name":"\u00cele Norfolk"},{"code":"AX","name":"\u00celes \u00c5land"},{"code":"KY","name":"\u00celes Ca\u00efmans"},{"code":"IC","name":"\u00celes Canaries"},{"code":"CC","name":"\u00celes Cocos"},{"code":"CK","name":"\u00celes Cook"},{"code":"FO","name":"\u00celes F\u00e9ro\u00e9"},{"code":"GS","name":"\u00celes G\u00e9orgie du Sud et Sandwich du Sud"},{"code":"FK","name":"\u00celes Malouines"},{"code":"MP","name":"\u00celes Mariannes du Nord"},{"code":"MH","name":"\u00celes Marshall"},{"code":"UM","name":"\u00celes mineures \u00e9loign\u00e9es des \u00c9tats-Unis"},{"code":"SB","name":"\u00celes Salomon"},{"code":"TC","name":"\u00celes Turques-et-Ca\u00efques"},{"code":"VG","name":"\u00celes Vierges britanniques"},{"code":"VI","name":"\u00celes Vierges des \u00c9tats-Unis"},{"code":"IN","name":"Inde"},{"code":"ID","name":"Indon\u00e9sie"},{"code":"IQ","name":"Irak"},{"code":"IR","name":"Iran"},{"code":"IE","name":"Irlande"},{"code":"IS","name":"Islande"},{"code":"IL","name":"Isra\u00ebl"},{"code":"IT","name":"Italie"},{"code":"JM","name":"Jama\u00efque"},{"code":"JP","name":"Japon"},{"code":"JE","name":"Jersey"},{"code":"JO","name":"Jordanie"},{"code":"KZ","name":"Kazakhstan"},{"code":"KE","name":"Kenya"},{"code":"KG","name":"Kirghizistan"},{"code":"KI","name":"Kiribati"},{"code":"XK","name":"Kosovo"},{"code":"KW","name":"Kowe\u00eft"},{"code":"RE","name":"La R\u00e9union"},{"code":"LA","name":"Laos"},{"code":"LS","name":"Lesotho"},{"code":"LV","name":"Lettonie"},{"code":"LB","name":"Liban"},{"code":"LR","name":"Lib\u00e9ria"},{"code":"LY","name":"Libye"},{"code":"LI","name":"Liechtenstein"},{"code":"LT","name":"Lituanie"},{"code":"LU","name":"Luxembourg"},{"code":"MK","name":"Mac\u00e9doine"},{"code":"MG","name":"Madagascar"},{"code":"MY","name":"Malaisie"},{"code":"MW","name":"Malawi"},{"code":"MV","name":"Maldives"},{"code":"ML","name":"Mali"},{"code":"MT","name":"Malte"},{"code":"MA","name":"Maroc"},{"code":"MQ","name":"Martinique"},{"code":"MU","name":"Maurice"},{"code":"MR","name":"Mauritanie"},{"code":"YT","name":"Mayotte"},{"code":"MX","name":"Mexique"},{"code":"MD","name":"Moldavie"},{"code":"MC","name":"Monaco"},{"code":"MN","name":"Mongolie"},{"code":"ME","name":"Mont\u00e9n\u00e9gro"},{"code":"MS","name":"Montserrat"},{"code":"MZ","name":"Mozambique"},{"code":"MM","name":"Myanmar"},{"code":"NA","name":"Namibie"},{"code":"NR","name":"Nauru"},{"code":"NP","name":"N\u00e9pal"},{"code":"NI","name":"Nicaragua"},{"code":"NE","name":"Niger"},{"code":"NG","name":"Nig\u00e9ria"},{"code":"NU","name":"Niue"},{"code":"NO","name":"Norv\u00e8ge"},{"code":"NC","name":"Nouvelle-Cal\u00e9donie"},{"code":"NZ","name":"Nouvelle-Z\u00e9lande"},{"code":"OM","name":"Oman"},{"code":"UG","name":"Ouganda"},{"code":"UZ","name":"Ouzb\u00e9kistan"},{"code":"PK","name":"Pakistan"},{"code":"PW","name":"Palaos"},{"code":"PA","name":"Panama"},{"code":"PG","name":"Papouasie-Nouvelle-Guin\u00e9e"},{"code":"PY","name":"Paraguay"},{"code":"NL","name":"Pays-Bas"},{"code":"BQ","name":"Pays-Bas carib\u00e9ens"},{"code":"PE","name":"P\u00e9rou"},{"code":"PH","name":"Philippines"},{"code":"PN","name":"Pitcairn"},{"code":"PL","name":"Pologne"},{"code":"PF","name":"Polyn\u00e9sie fran\u00e7aise"},{"code":"PR","name":"Porto Rico"},{"code":"PT","name":"Portugal"},{"code":"QA","name":"Qatar"},{"code":"HK","name":"R.A.S. chinoise de Hong Kong"},{"code":"MO","name":"R.A.S. chinoise de Macao"},{"code":"CF","name":"R\u00e9publique centrafricaine"},{"code":"DO","name":"R\u00e9publique dominicaine"},{"code":"CZ","name":"R\u00e9publique tch\u00e8que"},{"code":"RO","name":"Roumanie"},{"code":"GB","name":"Royaume-Uni"},{"code":"RU","name":"Russie"},{"code":"RW","name":"Rwanda"},{"code":"EH","name":"Sahara occidental"},{"code":"BL","name":"Saint-Barth\u00e9lemy"},{"code":"KN","name":"Saint-Christophe-et-Ni\u00e9v\u00e8s"},{"code":"SM","name":"Saint-Marin"},{"code":"MF","name":"Saint-Martin (partie fran\u00e7aise)"},{"code":"SX","name":"Saint-Martin (partie n\u00e9erlandaise)"},{"code":"PM","name":"Saint-Pierre-et-Miquelon"},{"code":"VC","name":"Saint-Vincent-et-les-Grenadines"},{"code":"SH","name":"Sainte-H\u00e9l\u00e8ne"},{"code":"LC","name":"Sainte-Lucie"},{"code":"WS","name":"Samoa"},{"code":"AS","name":"Samoa am\u00e9ricaines"},{"code":"ST","name":"Sao Tom\u00e9-et-Principe"},{"code":"SN","name":"S\u00e9n\u00e9gal"},{"code":"RS","name":"Serbie"},{"code":"SC","name":"Seychelles"},{"code":"SL","name":"Sierra Leone"},{"code":"SG","name":"Singapour"},{"code":"SK","name":"Slovaquie"},{"code":"SI","name":"Slov\u00e9nie"},{"code":"SO","name":"Somalie"},{"code":"SD","name":"Soudan"},{"code":"SS","name":"Soudan du Sud"},{"code":"LK","name":"Sri Lanka"},{"code":"SE","name":"Su\u00e8de"},{"code":"CH","name":"Suisse"},{"code":"SR","name":"Suriname"},{"code":"SJ","name":"Svalbard et Jan Mayen"},{"code":"SZ","name":"Swaziland"},{"code":"SY","name":"Syrie"},{"code":"TJ","name":"Tadjikistan"},{"code":"TW","name":"Ta\u00efwan"},{"code":"TZ","name":"Tanzanie"},{"code":"TD","name":"Tchad"},{"code":"TF","name":"Terres australes fran\u00e7aises"},{"code":"IO","name":"Territoire britannique de l\u2019oc\u00e9an Indien"},{"code":"PS","name":"Territoires palestiniens"},{"code":"TH","name":"Tha\u00eflande"},{"code":"TL","name":"Timor oriental"},{"code":"TG","name":"Togo"},{"code":"TK","name":"Tokelau"},{"code":"TO","name":"Tonga"},{"code":"TT","name":"Trinit\u00e9-et-Tobago"},{"code":"TA","name":"Tristan da Cunha"},{"code":"TN","name":"Tunisie"},{"code":"TM","name":"Turkm\u00e9nistan"},{"code":"TR","name":"Turquie"},{"code":"TV","name":"Tuvalu"},{"code":"UA","name":"Ukraine"},{"code":"UY","name":"Uruguay"},{"code":"VU","name":"Vanuatu"},{"code":"VE","name":"Venezuela"},{"code":"VN","name":"Vietnam"},{"code":"WF","name":"Wallis-et-Futuna"},{"code":"YE","name":"Y\u00e9men"},{"code":"ZM","name":"Zambie"},{"code":"ZW","name":"Zimbabwe"}]