[{"code":"AZ","name":"Acerbaix\u00e1n"},{"code":"AF","name":"Afganist\u00e1n"},{"code":"AL","name":"Albania"},{"code":"DE","name":"Alema\u00f1a"},{"code":"AD","name":"Andorra"},{"code":"AO","name":"Angola"},{"code":"AI","name":"Anguila"},{"code":"AQ","name":"Ant\u00e1rtida"},{"code":"AG","name":"Antiga e Barbuda"},{"code":"SA","name":"Arabia Saudita"},{"code":"AM","name":"Armenia"},{"code":"AW","name":"Aruba"},{"code":"DZ","name":"Arxelia"},{"code":"AR","name":"Arxentina"},{"code":"AU","name":"Australia"},{"code":"AT","name":"Austria"},{"code":"BS","name":"Bahamas"},{"code":"BH","name":"Bahrein"},{"code":"BD","name":"Bangladesh"},{"code":"BB","name":"Barbados"},{"code":"BZ","name":"Belice"},{"code":"BE","name":"B\u00e9lxica"},{"code":"BJ","name":"Benin"},{"code":"BM","name":"Bermudas"},{"code":"BY","name":"Bielorrusia"},{"code":"BO","name":"Bolivia"},{"code":"BA","name":"Bosnia e Hercegovina"},{"code":"BW","name":"Botsuana"},{"code":"BR","name":"Brasil"},{"code":"BN","name":"Brunei"},{"code":"BG","name":"Bulgaria"},{"code":"BF","name":"Burkina Faso"},{"code":"BI","name":"Burundi"},{"code":"BT","name":"But\u00e1n"},{"code":"CV","name":"Cabo Verde"},{"code":"KH","name":"Cambodia"},{"code":"CM","name":"Camer\u00fan"},{"code":"CA","name":"Canad\u00e1"},{"code":"BQ","name":"Caribe neerland\u00e9s"},{"code":"EA","name":"Ceuta e Melilla"},{"code":"TD","name":"Chad"},{"code":"CL","name":"Chile"},{"code":"CN","name":"China"},{"code":"CY","name":"Chipre"},{"code":"VA","name":"Cidade do Vaticano"},{"code":"ZW","name":"Cimbabue"},{"code":"CO","name":"Colombia"},{"code":"KM","name":"Comores"},{"code":"CG","name":"Congo"},{"code":"KP","name":"Corea do Norte"},{"code":"KR","name":"Corea do Sur"},{"code":"CI","name":"Costa de Marfil"},{"code":"CR","name":"Costa Rica"},{"code":"HR","name":"Croacia"},{"code":"CU","name":"Cuba"},{"code":"CW","name":"Cura\u00e7ao"},{"code":"DG","name":"Diego Garc\u00eda"},{"code":"DK","name":"Dinamarca"},{"code":"DM","name":"Dominica"},{"code":"EC","name":"Ecuador"},{"code":"SV","name":"El Salvador"},{"code":"AE","name":"Emiratos \u00c1rabes Unidos"},{"code":"ER","name":"Eritrea"},{"code":"SK","name":"Eslovaquia"},{"code":"SI","name":"Eslovenia"},{"code":"ES","name":"Espa\u00f1a"},{"code":"US","name":"Estados Unidos de Am\u00e9rica"},{"code":"EE","name":"Estonia"},{"code":"ET","name":"Etiop\u00eda"},{"code":"EG","name":"Exipto"},{"code":"PH","name":"Filipinas"},{"code":"FI","name":"Finlandia"},{"code":"FJ","name":"Fixi"},{"code":"FR","name":"Francia"},{"code":"GA","name":"Gab\u00f3n"},{"code":"GM","name":"Gambia"},{"code":"GH","name":"Gana"},{"code":"GD","name":"Granada"},{"code":"GR","name":"Grecia"},{"code":"GL","name":"Grenlandia"},{"code":"GP","name":"Guadalupe"},{"code":"GU","name":"Guam"},{"code":"GT","name":"Guatemala"},{"code":"GG","name":"Guernsey"},{"code":"GY","name":"G\u00fciana"},{"code":"GF","name":"G\u00fciana Francesa"},{"code":"GN","name":"Guinea"},{"code":"GQ","name":"Guinea Ecuatorial"},{"code":"GW","name":"Guinea-Bissau"},{"code":"HT","name":"Hait\u00ed"},{"code":"HN","name":"Honduras"},{"code":"HK","name":"Hong Kong RAE de China"},{"code":"HU","name":"Hungr\u00eda"},{"code":"YE","name":"Iemen"},{"code":"CX","name":"Illa Christmas"},{"code":"AC","name":"Illa de Ascensi\u00f3n"},{"code":"IM","name":"Illa de Man"},{"code":"NF","name":"Illa Norfolk"},{"code":"AX","name":"Illas Aland"},{"code":"KY","name":"Illas Caim\u00e1n"},{"code":"IC","name":"Illas Canarias"},{"code":"CC","name":"Illas Cocos (Keeling)"},{"code":"CK","name":"Illas Cook"},{"code":"FO","name":"Illas Feroe"},{"code":"FK","name":"Illas Malvinas"},{"code":"MP","name":"Illas Marianas do norte"},{"code":"MH","name":"Illas Marshall"},{"code":"UM","name":"Illas Menores Distantes dos EUA."},{"code":"PN","name":"Illas Pitcairn"},{"code":"SB","name":"Illas Salom\u00f3n"},{"code":"TC","name":"Illas Turks e Caicos"},{"code":"VG","name":"Illas Virxes Brit\u00e1nicas"},{"code":"VI","name":"Illas Virxes Estadounidenses"},{"code":"IN","name":"India"},{"code":"ID","name":"Indonesia"},{"code":"IR","name":"Ir\u00e1n"},{"code":"IQ","name":"Iraq"},{"code":"IE","name":"Irlanda"},{"code":"IS","name":"Islandia"},{"code":"IL","name":"Israel"},{"code":"IT","name":"Italia"},{"code":"JE","name":"Jersey"},{"code":"KZ","name":"Kazakhstan"},{"code":"KI","name":"Kiribati"},{"code":"XK","name":"Kosovo"},{"code":"KW","name":"Kuwait"},{"code":"LA","name":"Laos"},{"code":"LS","name":"Lesotho"},{"code":"LV","name":"Letonia"},{"code":"LB","name":"L\u00edbano"},{"code":"LR","name":"Liberia"},{"code":"LY","name":"Libia"},{"code":"LI","name":"Liechtenstein"},{"code":"LT","name":"Lituania"},{"code":"LU","name":"Luxemburgo"},{"code":"MO","name":"Macau RAE de China"},{"code":"MK","name":"Macedonia"},{"code":"MG","name":"Madagascar"},{"code":"MY","name":"Malaisia"},{"code":"MW","name":"Malaui"},{"code":"MV","name":"Maldivas"},{"code":"ML","name":"Mali"},{"code":"MT","name":"Malta"},{"code":"MA","name":"Marrocos"},{"code":"MQ","name":"Martinica"},{"code":"MU","name":"Mauricio"},{"code":"MR","name":"Mauritania"},{"code":"YT","name":"Mayotte"},{"code":"MX","name":"M\u00e9xico"},{"code":"FM","name":"Micronesia"},{"code":"MD","name":"Moldova"},{"code":"MC","name":"M\u00f3naco"},{"code":"MN","name":"Mongolia"},{"code":"ME","name":"Montenegro"},{"code":"MS","name":"Montserrat"},{"code":"MZ","name":"Mozambique"},{"code":"MM","name":"Myanmar (Birmania)"},{"code":"NA","name":"Namibia"},{"code":"NR","name":"Nauru"},{"code":"NP","name":"Nepal"},{"code":"NI","name":"Nicaragua"},{"code":"NU","name":"Niue"},{"code":"NE","name":"N\u00edxer"},{"code":"NG","name":"Nixeria"},{"code":"NO","name":"Noruega"},{"code":"NC","name":"Nova Caledonia"},{"code":"NZ","name":"Nova Celandia"},{"code":"OM","name":"Om\u00e1n"},{"code":"NL","name":"Pa\u00edses Baixos"},{"code":"PW","name":"Palau"},{"code":"PA","name":"Panam\u00e1"},{"code":"PG","name":"Pap\u00faa Nova Guinea"},{"code":"PK","name":"Paquist\u00e1n"},{"code":"PY","name":"Paraguai"},{"code":"PE","name":"Per\u00fa"},{"code":"PF","name":"Polinesia Francesa"},{"code":"PL","name":"Polonia"},{"code":"PR","name":"Porto Rico"},{"code":"PT","name":"Portugal"},{"code":"QA","name":"Qatar"},{"code":"KE","name":"Quenia"},{"code":"KG","name":"Quirguicist\u00e1n"},{"code":"GB","name":"Reino Unido"},{"code":"CF","name":"Rep\u00fablica Africana Central"},{"code":"CZ","name":"Rep\u00fablica Checa"},{"code":"CD","name":"Rep\u00fablica Democr\u00e1tica do Congo"},{"code":"DO","name":"Rep\u00fablica Dominicana"},{"code":"RE","name":"Reuni\u00f3n"},{"code":"RO","name":"Roman\u00eda"},{"code":"RW","name":"Ruanda"},{"code":"RU","name":"Rusia"},{"code":"EH","name":"Sahara Occidental"},{"code":"WS","name":"Samoa"},{"code":"AS","name":"Samoa Americana"},{"code":"BL","name":"San Bartolom\u00e9"},{"code":"KN","name":"San Cristovo e Nevis"},{"code":"SM","name":"San Marino"},{"code":"MF","name":"San Marti\u00f1o"},{"code":"PM","name":"San Pedro e Miguel\u00f3n"},{"code":"ST","name":"San Tom\u00e9 e Pr\u00edncipe"},{"code":"VC","name":"San Vicente e Granadinas"},{"code":"SH","name":"Santa Helena"},{"code":"LC","name":"Santa Luc\u00eda"},{"code":"SC","name":"Seixeles"},{"code":"SN","name":"Senegal"},{"code":"RS","name":"Serbia"},{"code":"SL","name":"Serra Leoa"},{"code":"SG","name":"Singapur"},{"code":"SX","name":"Sint Maarten"},{"code":"SY","name":"Siria"},{"code":"SO","name":"Somalia"},{"code":"LK","name":"Sri Lanka"},{"code":"SZ","name":"Suacilandia"},{"code":"ZA","name":"Sud\u00e1frica"},{"code":"SD","name":"Sud\u00e1n"},{"code":"SS","name":"Sud\u00e1n do sur"},{"code":"SE","name":"Suecia"},{"code":"CH","name":"Su\u00edza"},{"code":"SR","name":"Surinam"},{"code":"SJ","name":"Svalbard e Jan Mayen"},{"code":"TH","name":"Tailandia"},{"code":"TW","name":"Taiw\u00e1n"},{"code":"TZ","name":"Tanzania"},{"code":"TJ","name":"Taxiquist\u00e1n"},{"code":"IO","name":"Territorio Brit\u00e1nico do Oc\u00e9ano \u00cdndico"},{"code":"TF","name":"Territorios Franceses do Sul"},{"code":"PS","name":"Territorios palestinos"},{"code":"TL","name":"Timor Leste"},{"code":"TG","name":"Togo"},{"code":"TK","name":"Tokelau"},{"code":"TO","name":"Tonga"},{"code":"TT","name":"Trindade e Tobago"},{"code":"TA","name":"Trist\u00e1n da Cunha"},{"code":"TN","name":"Tunisia"},{"code":"TM","name":"Turkmenist\u00e1n"},{"code":"TR","name":"Turqu\u00eda"},{"code":"TV","name":"Tuvalu"},{"code":"UA","name":"Ucra\u00edna"},{"code":"UG","name":"Uganda"},{"code":"UY","name":"Uruguai"},{"code":"UZ","name":"Uzbekist\u00e1n"},{"code":"VU","name":"Vanuatu"},{"code":"VE","name":"Venezuela"},{"code":"VN","name":"Vietnam"},{"code":"WF","name":"Wallis e Futuna"},{"code":"JM","name":"Xamaica"},{"code":"JP","name":"Xap\u00f3n"},{"code":"GE","name":"Xeorxia"},{"code":"GS","name":"Xeorxia do Sur e Illas Sandwich"},{"code":"GI","name":"Xibraltar"},{"code":"DJ","name":"Xibuti"},{"code":"JO","name":"Xordania"},{"code":"ZM","name":"Zambia"}]